[[{"py/object": "datetime.datetime", "__reduce__": [{"py/type": "datetime.datetime"}, ["B+MFEQsAAAAAAA=="]]}, 34.5], [{"py/object": "datetime.datetime", "__reduce__": [{"py/type": "datetime.datetime"}, ["B+MFEQsGLwAAAA=="]]}, 34.1], [{"py/object": "datetime.datetime", "__reduce__": [{"py/type": "datetime.datetime"}, ["B+MFEQsIFgAAAA=="]]}, 33.82], [{"py/object": "datetime.datetime", "__reduce__": [{"py/type": "datetime.datetime"}, ["B+MFEQsKKQAAAA=="]]}, 33.82], [{"py/object": "datetime.datetime", "__reduce__": [{"py/type": "datetime.datetime"}, ["B+MFEQsLGwAAAA=="]]}, 33.9], [{"py/object": "datetime.datetime", "__reduce__": [{"py/type": "datetime.datetime"}, ["B+MFEQsODAAAAA=="]]}, 33.98], [{"py/object": "datetime.datetime", "__reduce__": [{"py/type": "datetime.datetime"}, ["B+MFEQsSOgAAAA=="]]}, 33.9], [{"py/object": "datetime.datetime", "__reduce__": [{"py/type": "datetime.datetime"}, ["B+MFEQsWKwAAAA=="]]}, 33.9], [{"py/object": "datetime.datetime", "__reduce__": [{"py/type": "datetime.datetime"}, ["B+MFEQsiNwAAAA=="]]}, 33.9], [{"py/object": "datetime.datetime", "__reduce__": [{"py/type": "datetime.datetime"}, ["B+MFEQsjOQAAAA=="]]}, 33.98], [{"py/object": "datetime.datetime", "__reduce__": [{"py/type": "datetime.datetime"}, ["B+MFEQsuGQAAAA=="]]}, 33.8], [{"py/object": "datetime.datetime", "__reduce__": [{"py/type": "datetime.datetime"}, ["B+MFEQs2KwAAAA=="]]}, 34], [{"py/object": "datetime.datetime", "__reduce__": [{"py/type": "datetime.datetime"}, ["B+MFEQs3EAAAAA=="]]}, 34], [{"py/object": "datetime.datetime", "__reduce__": [{"py/type": "datetime.datetime"}, ["B+MFEQwGHQAAAA=="]]}, 33.8], [{"py/object": "datetime.datetime", "__reduce__": [{"py/type": "datetime.datetime"}, ["B+MFEQwHKgAAAA=="]]}, 33.8], [{"py/object": "datetime.datetime", "__reduce__": [{"py/type": "datetime.datetime"}, ["B+MFEQwMNwAAAA=="]]}, 33.9], [{"py/object": "datetime.datetime", "__reduce__": [{"py/type": "datetime.datetime"}, ["B+MFEQwPKAAAAA=="]]}, 33.9], [{"py/object": "datetime.datetime", "__reduce__": [{"py/type": "datetime.datetime"}, ["B+MFEQwfGQAAAA=="]]}, 33.9], [{"py/object": "datetime.datetime", "__reduce__": [{"py/type": "datetime.datetime"}, ["B+MFEQwhHQAAAA=="]]}, 33.9], [{"py/object": "datetime.datetime", "__reduce__": [{"py/type": "datetime.datetime"}, ["B+MFEQwuDwAAAA=="]]}, 33.9], [{"py/object": "datetime.datetime", "__reduce__": [{"py/type": "datetime.datetime"}, ["B+MFEQwvAAAAAA=="]]}, 34.02], [{"py/object": "datetime.datetime", "__reduce__": [{"py/type": "datetime.datetime"}, ["B+MFEQw1IQAAAA=="]]}, 34], [{"py/object": "datetime.datetime", "__reduce__": [{"py/type": "datetime.datetime"}, ["B+MFEQw4NwAAAA=="]]}, 33.82], [{"py/object": "datetime.datetime", "__reduce__": [{"py/type": "datetime.datetime"}, ["B+MFEQ0GLwAAAA=="]]}, 33.9], [{"py/object": "datetime.datetime", "__reduce__": [{"py/type": "datetime.datetime"}, ["B+MFEQ0UAwAAAA=="]]}, 33.9], [{"py/object": "datetime.datetime", "__reduce__": [{"py/type": "datetime.datetime"}, ["B+MFEQ0aHQAAAA=="]]}, 33.9], [{"py/object": "datetime.datetime", "__reduce__": [{"py/type": "datetime.datetime"}, ["B+MFEQ0iCAAAAA=="]]}, 34.22], [{"py/object": "datetime.datetime", "__reduce__": [{"py/type": "datetime.datetime"}, ["B+MFEQ0kHAAAAA=="]]}, 33.96], [{"py/object": "datetime.datetime", "__reduce__": [{"py/type": "datetime.datetime"}, ["B+MFEQ0lDgAAAA=="]]}, 33.96], [{"py/object": "datetime.datetime", "__reduce__": [{"py/type": "datetime.datetime"}, ["B+MFEQ0oGAAAAA=="]]}, 33.96], [{"py/object": "datetime.datetime", "__reduce__": [{"py/type": "datetime.datetime"}, ["B+MFEQ0yGgAAAA=="]]}, 34.2], [{"py/object": "datetime.datetime", "__reduce__": [{"py/type": "datetime.datetime"}, ["B+MFEQ02DAAAAA=="]]}, 34.28], [{"py/object": "datetime.datetime", "__reduce__": [{"py/type": "datetime.datetime"}, ["B+MFEQ04LwAAAA=="]]}, 34.28], [{"py/object": "datetime.datetime", "__reduce__": [{"py/type": "datetime.datetime"}, ["B+MFEQ06JAAAAA=="]]}, 34], [{"py/object": "datetime.datetime", "__reduce__": [{"py/type": "datetime.datetime"}, ["B+MFEQ4ACwAAAA=="]]}, 34.3], [{"py/object": "datetime.datetime", "__reduce__": [{"py/type": "datetime.datetime"}, ["B+MFEQ4EKgAAAA=="]]}, 34.32], [{"py/object": "datetime.datetime", "__reduce__": [{"py/type": "datetime.datetime"}, ["B+MFEQ4GMgAAAA=="]]}, 34.34], [{"py/object": "datetime.datetime", "__reduce__": [{"py/type": "datetime.datetime"}, ["B+MFEQ4HBAAAAA=="]]}, 34.34], [{"py/object": "datetime.datetime", "__reduce__": [{"py/type": "datetime.datetime"}, ["B+MFEQ4MKwAAAA=="]]}, 34.34], [{"py/object": "datetime.datetime", "__reduce__": [{"py/type": "datetime.datetime"}, ["B+MFEQ4TOwAAAA=="]]}, 34.42], [{"py/object": "datetime.datetime", "__reduce__": [{"py/type": "datetime.datetime"}, ["B+MFEQ4UOAAAAA=="]]}, 34.44], [{"py/object": "datetime.datetime", "__reduce__": [{"py/type": "datetime.datetime"}, ["B+MFEQ4ZLgAAAA=="]]}, 34.44], [{"py/object": "datetime.datetime", "__reduce__": [{"py/type": "datetime.datetime"}, ["B+MFEQ4cMgAAAA=="]]}, 34.44], [{"py/object": "datetime.datetime", "__reduce__": [{"py/type": "datetime.datetime"}, ["B+MFEQ4gJQAAAA=="]]}, 34.56], [{"py/object": "datetime.datetime", "__reduce__": [{"py/type": "datetime.datetime"}, ["B+MFEQ4iGwAAAA=="]]}, 34.46], [{"py/object": "datetime.datetime", "__reduce__": [{"py/type": "datetime.datetime"}, ["B+MFEQ4lDwAAAA=="]]}, 34.46], [{"py/object": "datetime.datetime", "__reduce__": [{"py/type": "datetime.datetime"}, ["B+MFEQ4nKwAAAA=="]]}, 34.46], [{"py/object": "datetime.datetime", "__reduce__": [{"py/type": "datetime.datetime"}, ["B+MFEQ4tCwAAAA=="]]}, 34.46], [{"py/object": "datetime.datetime", "__reduce__": [{"py/type": "datetime.datetime"}, ["B+MFEQ4vDQAAAA=="]]}, 34.66], [{"py/object": "datetime.datetime", "__reduce__": [{"py/type": "datetime.datetime"}, ["B+MFEQ4xIgAAAA=="]]}, 34.64], [{"py/object": "datetime.datetime", "__reduce__": [{"py/type": "datetime.datetime"}, ["B+MFEQ4zFgAAAA=="]]}, 34.64], [{"py/object": "datetime.datetime", "__reduce__": [{"py/type": "datetime.datetime"}, ["B+MFEQ45LgAAAA=="]]}, 34.5], [{"py/object": "datetime.datetime", "__reduce__": [{"py/type": "datetime.datetime"}, ["B+MFEQ8CIgAAAA=="]]}, 34.62], [{"py/object": "datetime.datetime", "__reduce__": [{"py/type": "datetime.datetime"}, ["B+MFEQ8DBgAAAA=="]]}, 34.5], [{"py/object": "datetime.datetime", "__reduce__": [{"py/type": "datetime.datetime"}, ["B+MFEQ8LKgAAAA=="]]}, 34.4], [{"py/object": "datetime.datetime", "__reduce__": [{"py/type": "datetime.datetime"}, ["B+MFEQ8ROAAAAA=="]]}, 34.56], [{"py/object": "datetime.datetime", "__reduce__": [{"py/type": "datetime.datetime"}, ["B+MFEQ8UKAAAAA=="]]}, 34.56], [{"py/object": "datetime.datetime", "__reduce__": [{"py/type": "datetime.datetime"}, ["B+MFEQ8UNwAAAA=="]]}, 34.56], [{"py/object": "datetime.datetime", "__reduce__": [{"py/type": "datetime.datetime"}, ["B+MFEQ8ZAwAAAA=="]]}, 34.56], [{"py/object": "datetime.datetime", "__reduce__": [{"py/type": "datetime.datetime"}, ["B+MFEQ8cBQAAAA=="]]}, 34.32], [{"py/object": "datetime.datetime", "__reduce__": [{"py/type": "datetime.datetime"}, ["B+MFEQ8dIwAAAA=="]]}, 34.48], [{"py/object": "datetime.datetime", "__reduce__": [{"py/type": "datetime.datetime"}, ["B+MFEQ8mHwAAAA=="]]}, 34.2], [{"py/object": "datetime.datetime", "__reduce__": [{"py/type": "datetime.datetime"}, ["B+MFEQ8oIwAAAA=="]]}, 34.4], [{"py/object": "datetime.datetime", "__reduce__": [{"py/type": "datetime.datetime"}, ["B+MFEQ8vEAAAAA=="]]}, 34.4], [{"py/object": "datetime.datetime", "__reduce__": [{"py/type": "datetime.datetime"}, ["B+MFEQ8yCwAAAA=="]]}, 34.5], [{"py/object": "datetime.datetime", "__reduce__": [{"py/type": "datetime.datetime"}, ["B+MFERAVMwAAAA=="]]}, 34.5], [{"py/object": "datetime.datetime", "__reduce__": [{"py/type": "datetime.datetime"}, ["B+MFERAdAwAAAA=="]]}, 34.34], [{"py/object": "datetime.datetime", "__reduce__": [{"py/type": "datetime.datetime"}, ["B+MFERAmEQAAAA=="]]}, 34.44], [{"py/object": "datetime.datetime", "__reduce__": [{"py/type": "datetime.datetime"}, ["B+MFERApDQAAAA=="]]}, 34.48], [{"py/object": "datetime.datetime", "__reduce__": [{"py/type": "datetime.datetime"}, ["B+MFERAtNgAAAA=="]]}, 34.5], [{"py/object": "datetime.datetime", "__reduce__": [{"py/type": "datetime.datetime"}, ["B+MFERA5FAAAAA=="]]}, 34.52], [{"py/object": "datetime.datetime", "__reduce__": [{"py/type": "datetime.datetime"}, ["B+MFERA7HAAAAA=="]]}, 34.52], [{"py/object": "datetime.datetime", "__reduce__": [{"py/type": "datetime.datetime"}, ["B+MFEREBJAAAAA=="]]}, 34.26], [{"py/object": "datetime.datetime", "__reduce__": [{"py/type": "datetime.datetime"}, ["B+MFERENNAAAAA=="]]}, 34.24], [{"py/object": "datetime.datetime", "__reduce__": [{"py/type": "datetime.datetime"}, ["B+MFEREaJgAAAA=="]]}, 34.24], [{"py/object": "datetime.datetime", "__reduce__": [{"py/type": "datetime.datetime"}, ["B+MFEREdJgAAAA=="]]}, 34.14], [{"py/object": "datetime.datetime", "__reduce__": [{"py/type": "datetime.datetime"}, ["B+MFEREgIwAAAA=="]]}, 34.3], [{"py/object": "datetime.datetime", "__reduce__": [{"py/type": "datetime.datetime"}, ["B+MFEREiHwAAAA=="]]}, 34.32], [{"py/object": "datetime.datetime", "__reduce__": [{"py/type": "datetime.datetime"}, ["B+MFEREmEgAAAA=="]]}, 34.4], [{"py/object": "datetime.datetime", "__reduce__": [{"py/type": "datetime.datetime"}, ["B+MFEREoLQAAAA=="]]}, 34.3], [{"py/object": "datetime.datetime", "__reduce__": [{"py/type": "datetime.datetime"}, ["B+MFEREqLAAAAA=="]]}, 34.46], [{"py/object": "datetime.datetime", "__reduce__": [{"py/type": "datetime.datetime"}, ["B+MFERErLQAAAA=="]]}, 34.4], [{"py/object": "datetime.datetime", "__reduce__": [{"py/type": "datetime.datetime"}, ["B+MFEREsOQAAAA=="]]}, 34.4], [{"py/object": "datetime.datetime", "__reduce__": [{"py/type": "datetime.datetime"}, ["B+MFERE6NQAAAA=="]]}, 34.38], [{"py/object": "datetime.datetime", "__reduce__": [{"py/type": "datetime.datetime"}, ["B+MFERIAAAAAAA=="]]}, 34.46], [{"py/object": "datetime.datetime", "__reduce__": [{"py/type": "datetime.datetime"}, ["B+MFERIIJwAAAA=="]]}, 34.46], [{"py/object": "datetime.datetime", "__reduce__": [{"py/type": "datetime.datetime"}, ["B+MFERIMDAAAAA=="]]}, 34.12], [{"py/object": "datetime.datetime", "__reduce__": [{"py/type": "datetime.datetime"}, ["B+MFERINAQAAAA=="]]}, 34.08], [{"py/object": "datetime.datetime", "__reduce__": [{"py/type": "datetime.datetime"}, ["B+MFERIPBAAAAA=="]]}, 34.02], [{"py/object": "datetime.datetime", "__reduce__": [{"py/type": "datetime.datetime"}, ["B+MFERISAAAAAA=="]]}, 33.94], [{"py/object": "datetime.datetime", "__reduce__": [{"py/type": "datetime.datetime"}, ["B+MFERIWEgAAAA=="]]}, 34.12], [{"py/object": "datetime.datetime", "__reduce__": [{"py/type": "datetime.datetime"}, ["B+MFERIYCAAAAA=="]]}, 34.2], [{"py/object": "datetime.datetime", "__reduce__": [{"py/type": "datetime.datetime"}, ["B+MFERIZIwAAAA=="]]}, 34.22], [{"py/object": "datetime.datetime", "__reduce__": [{"py/type": "datetime.datetime"}, ["B+MFERIgHQAAAA=="]]}, 34.12], [{"py/object": "datetime.datetime", "__reduce__": [{"py/type": "datetime.datetime"}, ["B+MFERIhLAAAAA=="]]}, 34.04], [{"py/object": "datetime.datetime", "__reduce__": [{"py/type": "datetime.datetime"}, ["B+MFERIkDgAAAA=="]]}, 34.12], [{"py/object": "datetime.datetime", "__reduce__": [{"py/type": "datetime.datetime"}, ["B+MFERImLAAAAA=="]]}, 34.06], [{"py/object": "datetime.datetime", "__reduce__": [{"py/type": "datetime.datetime"}, ["B+MFERIoLAAAAA=="]]}, 33.92], [{"py/object": "datetime.datetime", "__reduce__": [{"py/type": "datetime.datetime"}, ["B+MFERIqBwAAAA=="]]}, 34.06], [{"py/object": "datetime.datetime", "__reduce__": [{"py/type": "datetime.datetime"}, ["B+MFERIsCQAAAA=="]]}, 34.04], [{"py/object": "datetime.datetime", "__reduce__": [{"py/type": "datetime.datetime"}, ["B+MFERIuIwAAAA=="]]}, 33.92], [{"py/object": "datetime.datetime", "__reduce__": [{"py/type": "datetime.datetime"}, ["B+MFERIvJQAAAA=="]]}, 34.18], [{"py/object": "datetime.datetime", "__reduce__": [{"py/type": "datetime.datetime"}, ["B+MFERIxLwAAAA=="]]}, 33.96], [{"py/object": "datetime.datetime", "__reduce__": [{"py/type": "datetime.datetime"}, ["B+MFERMAAAAAAA=="]]}, 34], [{"py/object": "datetime.datetime", "__reduce__": [{"py/type": "datetime.datetime"}, ["B+MFFAsAAAAAAA=="]]}, 34], [{"py/object": "datetime.datetime", "__reduce__": [{"py/type": "datetime.datetime"}, ["B+MFFAsGHAAAAA=="]]}, 34.28], [{"py/object": "datetime.datetime", "__reduce__": [{"py/type": "datetime.datetime"}, ["B+MFFAsKKQAAAA=="]]}, 34.12], [{"py/object": "datetime.datetime", "__reduce__": [{"py/type": "datetime.datetime"}, ["B+MFFAsYFAAAAA=="]]}, 34.26], [{"py/object": "datetime.datetime", "__reduce__": [{"py/type": "datetime.datetime"}, ["B+MFFAsaGQAAAA=="]]}, 33.96], [{"py/object": "datetime.datetime", "__reduce__": [{"py/type": "datetime.datetime"}, ["B+MFFAscLwAAAA=="]]}, 34], [{"py/object": "datetime.datetime", "__reduce__": [{"py/type": "datetime.datetime"}, ["B+MFFAsfKwAAAA=="]]}, 34], [{"py/object": "datetime.datetime", "__reduce__": [{"py/type": "datetime.datetime"}, ["B+MFFAsoGAAAAA=="]]}, 34.1], [{"py/object": "datetime.datetime", "__reduce__": [{"py/type": "datetime.datetime"}, ["B+MFFAsvBQAAAA=="]]}, 34.1], [{"py/object": "datetime.datetime", "__reduce__": [{"py/type": "datetime.datetime"}, ["B+MFFAs0MgAAAA=="]]}, 34], [{"py/object": "datetime.datetime", "__reduce__": [{"py/type": "datetime.datetime"}, ["B+MFFAwBJgAAAA=="]]}, 34.08], [{"py/object": "datetime.datetime", "__reduce__": [{"py/type": "datetime.datetime"}, ["B+MFFAwIFgAAAA=="]]}, 34.1], [{"py/object": "datetime.datetime", "__reduce__": [{"py/type": "datetime.datetime"}, ["B+MFFAwKDwAAAA=="]]}, 34.1], [{"py/object": "datetime.datetime", "__reduce__": [{"py/type": "datetime.datetime"}, ["B+MFFAwRMAAAAA=="]]}, 34.1], [{"py/object": "datetime.datetime", "__reduce__": [{"py/type": "datetime.datetime"}, ["B+MFFAwUIwAAAA=="]]}, 34], [{"py/object": "datetime.datetime", "__reduce__": [{"py/type": "datetime.datetime"}, ["B+MFFAwbFAAAAA=="]]}, 34.02], [{"py/object": "datetime.datetime", "__reduce__": [{"py/type": "datetime.datetime"}, ["B+MFFAwjNQAAAA=="]]}, 34.18], [{"py/object": "datetime.datetime", "__reduce__": [{"py/type": "datetime.datetime"}, ["B+MFFAwpCwAAAA=="]]}, 34.28], [{"py/object": "datetime.datetime", "__reduce__": [{"py/type": "datetime.datetime"}, ["B+MFFAwyCgAAAA=="]]}, 34.28], [{"py/object": "datetime.datetime", "__reduce__": [{"py/type": "datetime.datetime"}, ["B+MFFAwyMQAAAA=="]]}, 34.28], [{"py/object": "datetime.datetime", "__reduce__": [{"py/type": "datetime.datetime"}, ["B+MFFA0GEgAAAA=="]]}, 34.28], [{"py/object": "datetime.datetime", "__reduce__": [{"py/type": "datetime.datetime"}, ["B+MFFA0JAQAAAA=="]]}, 34.28], [{"py/object": "datetime.datetime", "__reduce__": [{"py/type": "datetime.datetime"}, ["B+MFFA0zAgAAAA=="]]}, 34.28], [{"py/object": "datetime.datetime", "__reduce__": [{"py/type": "datetime.datetime"}, ["B+MFFA4HEwAAAA=="]]}, 34.3], [{"py/object": "datetime.datetime", "__reduce__": [{"py/type": "datetime.datetime"}, ["B+MFFA4UAQAAAA=="]]}, 34.28], [{"py/object": "datetime.datetime", "__reduce__": [{"py/type": "datetime.datetime"}, ["B+MFFA4XLAAAAA=="]]}, 34.3], [{"py/object": "datetime.datetime", "__reduce__": [{"py/type": "datetime.datetime"}, ["B+MFFA4aHQAAAA=="]]}, 34.18], [{"py/object": "datetime.datetime", "__reduce__": [{"py/type": "datetime.datetime"}, ["B+MFFA4kBAAAAA=="]]}, 34.24], [{"py/object": "datetime.datetime", "__reduce__": [{"py/type": "datetime.datetime"}, ["B+MFFA8LCgAAAA=="]]}, 34.28], [{"py/object": "datetime.datetime", "__reduce__": [{"py/type": "datetime.datetime"}, ["B+MFFA8ROgAAAA=="]]}, 34.3], [{"py/object": "datetime.datetime", "__reduce__": [{"py/type": "datetime.datetime"}, ["B+MFFA8TMwAAAA=="]]}, 34.38], [{"py/object": "datetime.datetime", "__reduce__": [{"py/type": "datetime.datetime"}, ["B+MFFA8YGAAAAA=="]]}, 34.42], [{"py/object": "datetime.datetime", "__reduce__": [{"py/type": "datetime.datetime"}, ["B+MFFA8aLAAAAA=="]]}, 34.62], [{"py/object": "datetime.datetime", "__reduce__": [{"py/type": "datetime.datetime"}, ["B+MFFA8bEgAAAA=="]]}, 34.7], [{"py/object": "datetime.datetime", "__reduce__": [{"py/type": "datetime.datetime"}, ["B+MFFA8eEgAAAA=="]]}, 34.92], [{"py/object": "datetime.datetime", "__reduce__": [{"py/type": "datetime.datetime"}, ["B+MFFA8gJQAAAA=="]]}, 34.96], [{"py/object": "datetime.datetime", "__reduce__": [{"py/type": "datetime.datetime"}, ["B+MFFA8iFgAAAA=="]]}, 34.98], [{"py/object": "datetime.datetime", "__reduce__": [{"py/type": "datetime.datetime"}, ["B+MFFA8jLAAAAA=="]]}, 34.72], [{"py/object": "datetime.datetime", "__reduce__": [{"py/type": "datetime.datetime"}, ["B+MFFA8mLgAAAA=="]]}, 34.84], [{"py/object": "datetime.datetime", "__reduce__": [{"py/type": "datetime.datetime"}, ["B+MFFA8yLgAAAA=="]]}, 34.76], [{"py/object": "datetime.datetime", "__reduce__": [{"py/type": "datetime.datetime"}, ["B+MFFA8zFQAAAA=="]]}, 34.92], [{"py/object": "datetime.datetime", "__reduce__": [{"py/type": "datetime.datetime"}, ["B+MFFA82BgAAAA=="]]}, 34.86], [{"py/object": "datetime.datetime", "__reduce__": [{"py/type": "datetime.datetime"}, ["B+MFFBABCQAAAA=="]]}, 34.86], [{"py/object": "datetime.datetime", "__reduce__": [{"py/type": "datetime.datetime"}, ["B+MFFBAFJwAAAA=="]]}, 34.92], [{"py/object": "datetime.datetime", "__reduce__": [{"py/type": "datetime.datetime"}, ["B+MFFBASJwAAAA=="]]}, 34.86], [{"py/object": "datetime.datetime", "__reduce__": [{"py/type": "datetime.datetime"}, ["B+MFFBATCQAAAA=="]]}, 34.88], [{"py/object": "datetime.datetime", "__reduce__": [{"py/type": "datetime.datetime"}, ["B+MFFBAgDgAAAA=="]]}, 34.76], [{"py/object": "datetime.datetime", "__reduce__": [{"py/type": "datetime.datetime"}, ["B+MFFBAhBAAAAA=="]]}, 34.66], [{"py/object": "datetime.datetime", "__reduce__": [{"py/type": "datetime.datetime"}, ["B+MFFBApIQAAAA=="]]}, 34.74], [{"py/object": "datetime.datetime", "__reduce__": [{"py/type": "datetime.datetime"}, ["B+MFFBAsJgAAAA=="]]}, 34.62], [{"py/object": "datetime.datetime", "__reduce__": [{"py/type": "datetime.datetime"}, ["B+MFFBAsMQAAAA=="]]}, 34.54], [{"py/object": "datetime.datetime", "__reduce__": [{"py/type": "datetime.datetime"}, ["B+MFFBEBMgAAAA=="]]}, 34.5], [{"py/object": "datetime.datetime", "__reduce__": [{"py/type": "datetime.datetime"}, ["B+MFFBEHKAAAAA=="]]}, 34.5], [{"py/object": "datetime.datetime", "__reduce__": [{"py/type": "datetime.datetime"}, ["B+MFFBEKLQAAAA=="]]}, 34.5], [{"py/object": "datetime.datetime", "__reduce__": [{"py/type": "datetime.datetime"}, ["B+MFFBESGQAAAA=="]]}, 34.44], [{"py/object": "datetime.datetime", "__reduce__": [{"py/type": "datetime.datetime"}, ["B+MFFBEUFgAAAA=="]]}, 34.44], [{"py/object": "datetime.datetime", "__reduce__": [{"py/type": "datetime.datetime"}, ["B+MFFBEWLAAAAA=="]]}, 34.48], [{"py/object": "datetime.datetime", "__reduce__": [{"py/type": "datetime.datetime"}, ["B+MFFBEXGAAAAA=="]]}, 34.44], [{"py/object": "datetime.datetime", "__reduce__": [{"py/type": "datetime.datetime"}, ["B+MFFBEZCwAAAA=="]]}, 34.36], [{"py/object": "datetime.datetime", "__reduce__": [{"py/type": "datetime.datetime"}, ["B+MFFBEcBAAAAA=="]]}, 34.36], [{"py/object": "datetime.datetime", "__reduce__": [{"py/type": "datetime.datetime"}, ["B+MFFBEdKAAAAA=="]]}, 34.44], [{"py/object": "datetime.datetime", "__reduce__": [{"py/type": "datetime.datetime"}, ["B+MFFBEgMgAAAA=="]]}, 34.44], [{"py/object": "datetime.datetime", "__reduce__": [{"py/type": "datetime.datetime"}, ["B+MFFBElBgAAAA=="]]}, 34.3], [{"py/object": "datetime.datetime", "__reduce__": [{"py/type": "datetime.datetime"}, ["B+MFFBEsJwAAAA=="]]}, 34.4], [{"py/object": "datetime.datetime", "__reduce__": [{"py/type": "datetime.datetime"}, ["B+MFFBEtDAAAAA=="]]}, 34.44], [{"py/object": "datetime.datetime", "__reduce__": [{"py/type": "datetime.datetime"}, ["B+MFFBE1IgAAAA=="]]}, 34.44], [{"py/object": "datetime.datetime", "__reduce__": [{"py/type": "datetime.datetime"}, ["B+MFFBE4LQAAAA=="]]}, 34.28], [{"py/object": "datetime.datetime", "__reduce__": [{"py/type": "datetime.datetime"}, ["B+MFFBE5EQAAAA=="]]}, 34.26], [{"py/object": "datetime.datetime", "__reduce__": [{"py/type": "datetime.datetime"}, ["B+MFFBIOEQAAAA=="]]}, 34.46], [{"py/object": "datetime.datetime", "__reduce__": [{"py/type": "datetime.datetime"}, ["B+MFFBITLgAAAA=="]]}, 34.5], [{"py/object": "datetime.datetime", "__reduce__": [{"py/type": "datetime.datetime"}, ["B+MFFBIWIwAAAA=="]]}, 34.58], [{"py/object": "datetime.datetime", "__reduce__": [{"py/type": "datetime.datetime"}, ["B+MFFBIXFQAAAA=="]]}, 34.68], [{"py/object": "datetime.datetime", "__reduce__": [{"py/type": "datetime.datetime"}, ["B+MFFBIaKgAAAA=="]]}, 34.76], [{"py/object": "datetime.datetime", "__reduce__": [{"py/type": "datetime.datetime"}, ["B+MFFBIcLwAAAA=="]]}, 34.76], [{"py/object": "datetime.datetime", "__reduce__": [{"py/type": "datetime.datetime"}, ["B+MFFBIdKwAAAA=="]]}, 34.78], [{"py/object": "datetime.datetime", "__reduce__": [{"py/type": "datetime.datetime"}, ["B+MFFBImGQAAAA=="]]}, 34.66], [{"py/object": "datetime.datetime", "__reduce__": [{"py/type": "datetime.datetime"}, ["B+MFFBIoJAAAAA=="]]}, 34.74], [{"py/object": "datetime.datetime", "__reduce__": [{"py/type": "datetime.datetime"}, ["B+MFFBIqKwAAAA=="]]}, 34.8], [{"py/object": "datetime.datetime", "__reduce__": [{"py/type": "datetime.datetime"}, ["B+MFFBIrOwAAAA=="]]}, 34.7], [{"py/object": "datetime.datetime", "__reduce__": [{"py/type": "datetime.datetime"}, ["B+MFFBIuLAAAAA=="]]}, 34.76], [{"py/object": "datetime.datetime", "__reduce__": [{"py/type": "datetime.datetime"}, ["B+MFFBIxNwAAAA=="]]}, 34.68], [{"py/object": "datetime.datetime", "__reduce__": [{"py/type": "datetime.datetime"}, ["B+MFFBMAAAAAAA=="]]}, 34.84], [{"py/object": "datetime.datetime", "__reduce__": [{"py/type": "datetime.datetime"}, ["B+MFFBMDDgAAAA=="]]}, 34.84], [{"py/object": "datetime.datetime", "__reduce__": [{"py/type": "datetime.datetime"}, ["B+MFFQsAIAAAAA=="]]}, 34.94], [{"py/object": "datetime.datetime", "__reduce__": [{"py/type": "datetime.datetime"}, ["B+MFFQsIKwAAAA=="]]}, 34.94], [{"py/object": "datetime.datetime", "__reduce__": [{"py/type": "datetime.datetime"}, ["B+MFFQsKLQAAAA=="]]}, 34.94], [{"py/object": "datetime.datetime", "__reduce__": [{"py/type": "datetime.datetime"}, ["B+MFFQsLAgAAAA=="]]}, 35.2], [{"py/object": "datetime.datetime", "__reduce__": [{"py/type": "datetime.datetime"}, ["B+MFFQsOBQAAAA=="]]}, 35.12], [{"py/object": "datetime.datetime", "__reduce__": [{"py/type": "datetime.datetime"}, ["B+MFFQsWIAAAAA=="]]}, 35], [{"py/object": "datetime.datetime", "__reduce__": [{"py/type": "datetime.datetime"}, ["B+MFFQsbFAAAAA=="]]}, 35], [{"py/object": "datetime.datetime", "__reduce__": [{"py/type": "datetime.datetime"}, ["B+MFFQsfBQAAAA=="]]}, 35.16], [{"py/object": "datetime.datetime", "__reduce__": [{"py/type": "datetime.datetime"}, ["B+MFFQstEwAAAA=="]]}, 35.16], [{"py/object": "datetime.datetime", "__reduce__": [{"py/type": "datetime.datetime"}, ["B+MFFQsxEQAAAA=="]]}, 35.2], [{"py/object": "datetime.datetime", "__reduce__": [{"py/type": "datetime.datetime"}, ["B+MFFQs1DAAAAA=="]]}, 35.34], [{"py/object": "datetime.datetime", "__reduce__": [{"py/type": "datetime.datetime"}, ["B+MFFQwCHgAAAA=="]]}, 35.5], [{"py/object": "datetime.datetime", "__reduce__": [{"py/type": "datetime.datetime"}, ["B+MFFQwEHQAAAA=="]]}, 35.58], [{"py/object": "datetime.datetime", "__reduce__": [{"py/type": "datetime.datetime"}, ["B+MFFQwGGwAAAA=="]]}, 35.7], [{"py/object": "datetime.datetime", "__reduce__": [{"py/type": "datetime.datetime"}, ["B+MFFQwILQAAAA=="]]}, 35.64], [{"py/object": "datetime.datetime", "__reduce__": [{"py/type": "datetime.datetime"}, ["B+MFFQwJLQAAAA=="]]}, 35.66], [{"py/object": "datetime.datetime", "__reduce__": [{"py/type": "datetime.datetime"}, ["B+MFFQwLBwAAAA=="]]}, 35.7], [{"py/object": "datetime.datetime", "__reduce__": [{"py/type": "datetime.datetime"}, ["B+MFFQwNLwAAAA=="]]}, 35.74], [{"py/object": "datetime.datetime", "__reduce__": [{"py/type": "datetime.datetime"}, ["B+MFFQwPOQAAAA=="]]}, 35.78], [{"py/object": "datetime.datetime", "__reduce__": [{"py/type": "datetime.datetime"}, ["B+MFFQwSCQAAAA=="]]}, 35.78], [{"py/object": "datetime.datetime", "__reduce__": [{"py/type": "datetime.datetime"}, ["B+MFFQwUJwAAAA=="]]}, 35.78], [{"py/object": "datetime.datetime", "__reduce__": [{"py/type": "datetime.datetime"}, ["B+MFFQwYIAAAAA=="]]}, 35.78], [{"py/object": "datetime.datetime", "__reduce__": [{"py/type": "datetime.datetime"}, ["B+MFFQwZNwAAAA=="]]}, 35.92], [{"py/object": "datetime.datetime", "__reduce__": [{"py/type": "datetime.datetime"}, ["B+MFFQwcDQAAAA=="]]}, 35.8], [{"py/object": "datetime.datetime", "__reduce__": [{"py/type": "datetime.datetime"}, ["B+MFFQwgHwAAAA=="]]}, 36.12], [{"py/object": "datetime.datetime", "__reduce__": [{"py/type": "datetime.datetime"}, ["B+MFFQwiCQAAAA=="]]}, 36.1], [{"py/object": "datetime.datetime", "__reduce__": [{"py/type": "datetime.datetime"}, ["B+MFFQwkJwAAAA=="]]}, 36.1], [{"py/object": "datetime.datetime", "__reduce__": [{"py/type": "datetime.datetime"}, ["B+MFFQwmGAAAAA=="]]}, 35.96], [{"py/object": "datetime.datetime", "__reduce__": [{"py/type": "datetime.datetime"}, ["B+MFFQwrKAAAAA=="]]}, 36.28], [{"py/object": "datetime.datetime", "__reduce__": [{"py/type": "datetime.datetime"}, ["B+MFFQwuEgAAAA=="]]}, 36.32], [{"py/object": "datetime.datetime", "__reduce__": [{"py/type": "datetime.datetime"}, ["B+MFFQwvDgAAAA=="]]}, 36.08], [{"py/object": "datetime.datetime", "__reduce__": [{"py/type": "datetime.datetime"}, ["B+MFFQw0JwAAAA=="]]}, 36.26], [{"py/object": "datetime.datetime", "__reduce__": [{"py/type": "datetime.datetime"}, ["B+MFFQw1FgAAAA=="]]}, 36.32], [{"py/object": "datetime.datetime", "__reduce__": [{"py/type": "datetime.datetime"}, ["B+MFFQw4IgAAAA=="]]}, 36.34], [{"py/object": "datetime.datetime", "__reduce__": [{"py/type": "datetime.datetime"}, ["B+MFFQ0BEQAAAA=="]]}, 36.38], [{"py/object": "datetime.datetime", "__reduce__": [{"py/type": "datetime.datetime"}, ["B+MFFQ0DAAAAAA=="]]}, 36.26], [{"py/object": "datetime.datetime", "__reduce__": [{"py/type": "datetime.datetime"}, ["B+MFFQ0HMwAAAA=="]]}, 36.38], [{"py/object": "datetime.datetime", "__reduce__": [{"py/type": "datetime.datetime"}, ["B+MFFQ0OCgAAAA=="]]}, 36.08], [{"py/object": "datetime.datetime", "__reduce__": [{"py/type": "datetime.datetime"}, ["B+MFFQ0QHQAAAA=="]]}, 36.34], [{"py/object": "datetime.datetime", "__reduce__": [{"py/type": "datetime.datetime"}, ["B+MFFQ0RJwAAAA=="]]}, 36.36], [{"py/object": "datetime.datetime", "__reduce__": [{"py/type": "datetime.datetime"}, ["B+MFFQ0UEgAAAA=="]]}, 36.36], [{"py/object": "datetime.datetime", "__reduce__": [{"py/type": "datetime.datetime"}, ["B+MFFQ0ZCwAAAA=="]]}, 36.36], [{"py/object": "datetime.datetime", "__reduce__": [{"py/type": "datetime.datetime"}, ["B+MFFQ0cKQAAAA=="]]}, 36.3], [{"py/object": "datetime.datetime", "__reduce__": [{"py/type": "datetime.datetime"}, ["B+MFFQ0fOQAAAA=="]]}, 36.18], [{"py/object": "datetime.datetime", "__reduce__": [{"py/type": "datetime.datetime"}, ["B+MFFQ0iEwAAAA=="]]}, 36.18], [{"py/object": "datetime.datetime", "__reduce__": [{"py/type": "datetime.datetime"}, ["B+MFFQ0jNgAAAA=="]]}, 36.1], [{"py/object": "datetime.datetime", "__reduce__": [{"py/type": "datetime.datetime"}, ["B+MFFQ0oLQAAAA=="]]}, 36.2], [{"py/object": "datetime.datetime", "__reduce__": [{"py/type": "datetime.datetime"}, ["B+MFFQ0uDQAAAA=="]]}, 36.3], [{"py/object": "datetime.datetime", "__reduce__": [{"py/type": "datetime.datetime"}, ["B+MFFQ0xOQAAAA=="]]}, 36.3], [{"py/object": "datetime.datetime", "__reduce__": [{"py/type": "datetime.datetime"}, ["B+MFFQ4FFAAAAA=="]]}, 36.22], [{"py/object": "datetime.datetime", "__reduce__": [{"py/type": "datetime.datetime"}, ["B+MFFQ4PGQAAAA=="]]}, 36.3], [{"py/object": "datetime.datetime", "__reduce__": [{"py/type": "datetime.datetime"}, ["B+MFFQ4ROQAAAA=="]]}, 36.2], [{"py/object": "datetime.datetime", "__reduce__": [{"py/type": "datetime.datetime"}, ["B+MFFQ4UJgAAAA=="]]}, 36.28], [{"py/object": "datetime.datetime", "__reduce__": [{"py/type": "datetime.datetime"}, ["B+MFFQ4YEQAAAA=="]]}, 36.28], [{"py/object": "datetime.datetime", "__reduce__": [{"py/type": "datetime.datetime"}, ["B+MFFQ4hHwAAAA=="]]}, 36.28], [{"py/object": "datetime.datetime", "__reduce__": [{"py/type": "datetime.datetime"}, ["B+MFFQ4tEwAAAA=="]]}, 36.3], [{"py/object": "datetime.datetime", "__reduce__": [{"py/type": "datetime.datetime"}, ["B+MFFQ4yFQAAAA=="]]}, 36.3], [{"py/object": "datetime.datetime", "__reduce__": [{"py/type": "datetime.datetime"}, ["B+MFFQ40KAAAAA=="]]}, 36.34], [{"py/object": "datetime.datetime", "__reduce__": [{"py/type": "datetime.datetime"}, ["B+MFFQ44CQAAAA=="]]}, 36.38], [{"py/object": "datetime.datetime", "__reduce__": [{"py/type": "datetime.datetime"}, ["B+MFFQ45NgAAAA=="]]}, 36.3], [{"py/object": "datetime.datetime", "__reduce__": [{"py/type": "datetime.datetime"}, ["B+MFFQ8HKwAAAA=="]]}, 36.34], [{"py/object": "datetime.datetime", "__reduce__": [{"py/type": "datetime.datetime"}, ["B+MFFQ8PKgAAAA=="]]}, 36.32], [{"py/object": "datetime.datetime", "__reduce__": [{"py/type": "datetime.datetime"}, ["B+MFFQ8bEQAAAA=="]]}, 36.1], [{"py/object": "datetime.datetime", "__reduce__": [{"py/type": "datetime.datetime"}, ["B+MFFQ8mGwAAAA=="]]}, 36.3], [{"py/object": "datetime.datetime", "__reduce__": [{"py/type": "datetime.datetime"}, ["B+MFFQ8oBgAAAA=="]]}, 36.3], [{"py/object": "datetime.datetime", "__reduce__": [{"py/type": "datetime.datetime"}, ["B+MFFQ8qFAAAAA=="]]}, 36.3], [{"py/object": "datetime.datetime", "__reduce__": [{"py/type": "datetime.datetime"}, ["B+MFFQ8uDAAAAA=="]]}, 36.22], [{"py/object": "datetime.datetime", "__reduce__": [{"py/type": "datetime.datetime"}, ["B+MFFQ8wCwAAAA=="]]}, 36.22], [{"py/object": "datetime.datetime", "__reduce__": [{"py/type": "datetime.datetime"}, ["B+MFFQ83HQAAAA=="]]}, 36.3], [{"py/object": "datetime.datetime", "__reduce__": [{"py/type": "datetime.datetime"}, ["B+MFFQ84LgAAAA=="]]}, 36.16], [{"py/object": "datetime.datetime", "__reduce__": [{"py/type": "datetime.datetime"}, ["B+MFFQ87CwAAAA=="]]}, 36.28], [{"py/object": "datetime.datetime", "__reduce__": [{"py/type": "datetime.datetime"}, ["B+MFFRAEEQAAAA=="]]}, 36.1], [{"py/object": "datetime.datetime", "__reduce__": [{"py/type": "datetime.datetime"}, ["B+MFFRAIBwAAAA=="]]}, 36.26], [{"py/object": "datetime.datetime", "__reduce__": [{"py/type": "datetime.datetime"}, ["B+MFFRAMDQAAAA=="]]}, 36.26], [{"py/object": "datetime.datetime", "__reduce__": [{"py/type": "datetime.datetime"}, ["B+MFFRAPHQAAAA=="]]}, 36.3], [{"py/object": "datetime.datetime", "__reduce__": [{"py/type": "datetime.datetime"}, ["B+MFFRASGQAAAA=="]]}, 36.4], [{"py/object": "datetime.datetime", "__reduce__": [{"py/type": "datetime.datetime"}, ["B+MFFRATNwAAAA=="]]}, 36.38], [{"py/object": "datetime.datetime", "__reduce__": [{"py/type": "datetime.datetime"}, ["B+MFFRAWEAAAAA=="]]}, 36.38], [{"py/object": "datetime.datetime", "__reduce__": [{"py/type": "datetime.datetime"}, ["B+MFFRAXEgAAAA=="]]}, 36.38], [{"py/object": "datetime.datetime", "__reduce__": [{"py/type": "datetime.datetime"}, ["B+MFFRAZJAAAAA=="]]}, 36.38], [{"py/object": "datetime.datetime", "__reduce__": [{"py/type": "datetime.datetime"}, ["B+MFFRAbEgAAAA=="]]}, 36.36], [{"py/object": "datetime.datetime", "__reduce__": [{"py/type": "datetime.datetime"}, ["B+MFFRAeIAAAAA=="]]}, 36.42], [{"py/object": "datetime.datetime", "__reduce__": [{"py/type": "datetime.datetime"}, ["B+MFFRAfIQAAAA=="]]}, 36.44], [{"py/object": "datetime.datetime", "__reduce__": [{"py/type": "datetime.datetime"}, ["B+MFFRAhOQAAAA=="]]}, 36.7], [{"py/object": "datetime.datetime", "__reduce__": [{"py/type": "datetime.datetime"}, ["B+MFFRAkKgAAAA=="]]}, 37.12], [{"py/object": "datetime.datetime", "__reduce__": [{"py/type": "datetime.datetime"}, ["B+MFFRAmIAAAAA=="]]}, 37], [{"py/object": "datetime.datetime", "__reduce__": [{"py/type": "datetime.datetime"}, ["B+MFFRAsCQAAAA=="]]}, 37], [{"py/object": "datetime.datetime", "__reduce__": [{"py/type": "datetime.datetime"}, ["B+MFFRAuHAAAAA=="]]}, 37.12], [{"py/object": "datetime.datetime", "__reduce__": [{"py/type": "datetime.datetime"}, ["B+MFFRAwIQAAAA=="]]}, 37.2], [{"py/object": "datetime.datetime", "__reduce__": [{"py/type": "datetime.datetime"}, ["B+MFFRAyEgAAAA=="]]}, 37.38], [{"py/object": "datetime.datetime", "__reduce__": [{"py/type": "datetime.datetime"}, ["B+MFFRA0KwAAAA=="]]}, 37], [{"py/object": "datetime.datetime", "__reduce__": [{"py/type": "datetime.datetime"}, ["B+MFFRA1NgAAAA=="]]}, 37], [{"py/object": "datetime.datetime", "__reduce__": [{"py/type": "datetime.datetime"}, ["B+MFFRA3IgAAAA=="]]}, 37], [{"py/object": "datetime.datetime", "__reduce__": [{"py/type": "datetime.datetime"}, ["B+MFFRA5JQAAAA=="]]}, 36.84], [{"py/object": "datetime.datetime", "__reduce__": [{"py/type": "datetime.datetime"}, ["B+MFFRECJwAAAA=="]]}, 37], [{"py/object": "datetime.datetime", "__reduce__": [{"py/type": "datetime.datetime"}, ["B+MFFREDAQAAAA=="]]}, 36.94], [{"py/object": "datetime.datetime", "__reduce__": [{"py/type": "datetime.datetime"}, ["B+MFFREGFwAAAA=="]]}, 36.98], [{"py/object": "datetime.datetime", "__reduce__": [{"py/type": "datetime.datetime"}, ["B+MFFREHGAAAAA=="]]}, 36.96], [{"py/object": "datetime.datetime", "__reduce__": [{"py/type": "datetime.datetime"}, ["B+MFFRELKgAAAA=="]]}, 36.66], [{"py/object": "datetime.datetime", "__reduce__": [{"py/type": "datetime.datetime"}, ["B+MFFRENMAAAAA=="]]}, 36.76], [{"py/object": "datetime.datetime", "__reduce__": [{"py/type": "datetime.datetime"}, ["B+MFFREQBgAAAA=="]]}, 36.82], [{"py/object": "datetime.datetime", "__reduce__": [{"py/type": "datetime.datetime"}, ["B+MFFRESHAAAAA=="]]}, 36.66], [{"py/object": "datetime.datetime", "__reduce__": [{"py/type": "datetime.datetime"}, ["B+MFFRETKwAAAA=="]]}, 36.66], [{"py/object": "datetime.datetime", "__reduce__": [{"py/type": "datetime.datetime"}, ["B+MFFREVJQAAAA=="]]}, 36.5], [{"py/object": "datetime.datetime", "__reduce__": [{"py/type": "datetime.datetime"}, ["B+MFFREYBwAAAA=="]]}, 36.5], [{"py/object": "datetime.datetime", "__reduce__": [{"py/type": "datetime.datetime"}, ["B+MFFREbIgAAAA=="]]}, 36.58], [{"py/object": "datetime.datetime", "__reduce__": [{"py/type": "datetime.datetime"}, ["B+MFFREeAQAAAA=="]]}, 36.56], [{"py/object": "datetime.datetime", "__reduce__": [{"py/type": "datetime.datetime"}, ["B+MFFREgKgAAAA=="]]}, 36.5], [{"py/object": "datetime.datetime", "__reduce__": [{"py/type": "datetime.datetime"}, ["B+MFFREiAAAAAA=="]]}, 36.52], [{"py/object": "datetime.datetime", "__reduce__": [{"py/type": "datetime.datetime"}, ["B+MFFREkHAAAAA=="]]}, 36.54], [{"py/object": "datetime.datetime", "__reduce__": [{"py/type": "datetime.datetime"}, ["B+MFFRElOwAAAA=="]]}, 36.4], [{"py/object": "datetime.datetime", "__reduce__": [{"py/type": "datetime.datetime"}, ["B+MFFREoJQAAAA=="]]}, 36.4], [{"py/object": "datetime.datetime", "__reduce__": [{"py/type": "datetime.datetime"}, ["B+MFFREpGwAAAA=="]]}, 36.48], [{"py/object": "datetime.datetime", "__reduce__": [{"py/type": "datetime.datetime"}, ["B+MFFREsDQAAAA=="]]}, 36.42], [{"py/object": "datetime.datetime", "__reduce__": [{"py/type": "datetime.datetime"}, ["B+MFFREuAgAAAA=="]]}, 36.42], [{"py/object": "datetime.datetime", "__reduce__": [{"py/type": "datetime.datetime"}, ["B+MFFREwFgAAAA=="]]}, 36.24], [{"py/object": "datetime.datetime", "__reduce__": [{"py/type": "datetime.datetime"}, ["B+MFFREzFAAAAA=="]]}, 36.34], [{"py/object": "datetime.datetime", "__reduce__": [{"py/type": "datetime.datetime"}, ["B+MFFRE1JAAAAA=="]]}, 36.34], [{"py/object": "datetime.datetime", "__reduce__": [{"py/type": "datetime.datetime"}, ["B+MFFRE3GgAAAA=="]]}, 36.24], [{"py/object": "datetime.datetime", "__reduce__": [{"py/type": "datetime.datetime"}, ["B+MFFRE6FAAAAA=="]]}, 36.18], [{"py/object": "datetime.datetime", "__reduce__": [{"py/type": "datetime.datetime"}, ["B+MFFRE7JQAAAA=="]]}, 36.14], [{"py/object": "datetime.datetime", "__reduce__": [{"py/type": "datetime.datetime"}, ["B+MFFRIEIgAAAA=="]]}, 36.3], [{"py/object": "datetime.datetime", "__reduce__": [{"py/type": "datetime.datetime"}, ["B+MFFRIGBgAAAA=="]]}, 36.5], [{"py/object": "datetime.datetime", "__reduce__": [{"py/type": "datetime.datetime"}, ["B+MFFRIICAAAAA=="]]}, 36.48], [{"py/object": "datetime.datetime", "__reduce__": [{"py/type": "datetime.datetime"}, ["B+MFFRIKKQAAAA=="]]}, 36.46], [{"py/object": "datetime.datetime", "__reduce__": [{"py/type": "datetime.datetime"}, ["B+MFFRIMEAAAAA=="]]}, 36.46], [{"py/object": "datetime.datetime", "__reduce__": [{"py/type": "datetime.datetime"}, ["B+MFFRINFgAAAA=="]]}, 36.52], [{"py/object": "datetime.datetime", "__reduce__": [{"py/type": "datetime.datetime"}, ["B+MFFRIPHwAAAA=="]]}, 36.58], [{"py/object": "datetime.datetime", "__reduce__": [{"py/type": "datetime.datetime"}, ["B+MFFRISKwAAAA=="]]}, 36.58], [{"py/object": "datetime.datetime", "__reduce__": [{"py/type": "datetime.datetime"}, ["B+MFFRIUEQAAAA=="]]}, 36.58], [{"py/object": "datetime.datetime", "__reduce__": [{"py/type": "datetime.datetime"}, ["B+MFFRIWKQAAAA=="]]}, 36.56], [{"py/object": "datetime.datetime", "__reduce__": [{"py/type": "datetime.datetime"}, ["B+MFFRIXJgAAAA=="]]}, 36.6], [{"py/object": "datetime.datetime", "__reduce__": [{"py/type": "datetime.datetime"}, ["B+MFFRIZCQAAAA=="]]}, 36.68], [{"py/object": "datetime.datetime", "__reduce__": [{"py/type": "datetime.datetime"}, ["B+MFFRIbFAAAAA=="]]}, 36.66], [{"py/object": "datetime.datetime", "__reduce__": [{"py/type": "datetime.datetime"}, ["B+MFFRIeJwAAAA=="]]}, 36.64], [{"py/object": "datetime.datetime", "__reduce__": [{"py/type": "datetime.datetime"}, ["B+MFFRIgDAAAAA=="]]}, 36.7], [{"py/object": "datetime.datetime", "__reduce__": [{"py/type": "datetime.datetime"}, ["B+MFFRIiKwAAAA=="]]}, 36.7], [{"py/object": "datetime.datetime", "__reduce__": [{"py/type": "datetime.datetime"}, ["B+MFFRIkDgAAAA=="]]}, 36.68], [{"py/object": "datetime.datetime", "__reduce__": [{"py/type": "datetime.datetime"}, ["B+MFFRImIwAAAA=="]]}, 36.62], [{"py/object": "datetime.datetime", "__reduce__": [{"py/type": "datetime.datetime"}, ["B+MFFRInDAAAAA=="]]}, 36.7], [{"py/object": "datetime.datetime", "__reduce__": [{"py/type": "datetime.datetime"}, ["B+MFFRIpOwAAAA=="]]}, 36.6], [{"py/object": "datetime.datetime", "__reduce__": [{"py/type": "datetime.datetime"}, ["B+MFFRIsEQAAAA=="]]}, 36.7], [{"py/object": "datetime.datetime", "__reduce__": [{"py/type": "datetime.datetime"}, ["B+MFFRIuIgAAAA=="]]}, 36.7], [{"py/object": "datetime.datetime", "__reduce__": [{"py/type": "datetime.datetime"}, ["B+MFFRIwHwAAAA=="]]}, 36.7], [{"py/object": "datetime.datetime", "__reduce__": [{"py/type": "datetime.datetime"}, ["B+MFFRIxOgAAAA=="]]}, 36.66], [{"py/object": "datetime.datetime", "__reduce__": [{"py/type": "datetime.datetime"}, ["B+MFFRMAAAAAAA=="]]}, 36.7], [{"py/object": "datetime.datetime", "__reduce__": [{"py/type": "datetime.datetime"}, ["B+MFFRMCHAAAAA=="]]}, 36.7], [{"py/object": "datetime.datetime", "__reduce__": [{"py/type": "datetime.datetime"}, ["B+MFFgsAAAAAAA=="]]}, 36.92], [{"py/object": "datetime.datetime", "__reduce__": [{"py/type": "datetime.datetime"}, ["B+MFFgsBNwAAAA=="]]}, 36.92], [{"py/object": "datetime.datetime", "__reduce__": [{"py/type": "datetime.datetime"}, ["B+MFFgsDNQAAAA=="]]}, 37.18], [{"py/object": "datetime.datetime", "__reduce__": [{"py/type": "datetime.datetime"}, ["B+MFFgsFHwAAAA=="]]}, 37.2], [{"py/object": "datetime.datetime", "__reduce__": [{"py/type": "datetime.datetime"}, ["B+MFFgsICQAAAA=="]]}, 37.24], [{"py/object": "datetime.datetime", "__reduce__": [{"py/type": "datetime.datetime"}, ["B+MFFgsKBwAAAA=="]]}, 37.24], [{"py/object": "datetime.datetime", "__reduce__": [{"py/type": "datetime.datetime"}, ["B+MFFgsMCgAAAA=="]]}, 37.24], [{"py/object": "datetime.datetime", "__reduce__": [{"py/type": "datetime.datetime"}, ["B+MFFgsNJwAAAA=="]]}, 37.24], [{"py/object": "datetime.datetime", "__reduce__": [{"py/type": "datetime.datetime"}, ["B+MFFgsOOwAAAA=="]]}, 37.24], [{"py/object": "datetime.datetime", "__reduce__": [{"py/type": "datetime.datetime"}, ["B+MFFgsRGgAAAA=="]]}, 37.1], [{"py/object": "datetime.datetime", "__reduce__": [{"py/type": "datetime.datetime"}, ["B+MFFgsUFAAAAA=="]]}, 37], [{"py/object": "datetime.datetime", "__reduce__": [{"py/type": "datetime.datetime"}, ["B+MFFgsVLgAAAA=="]]}, 36.92], [{"py/object": "datetime.datetime", "__reduce__": [{"py/type": "datetime.datetime"}, ["B+MFFgsYHgAAAA=="]]}, 37.16], [{"py/object": "datetime.datetime", "__reduce__": [{"py/type": "datetime.datetime"}, ["B+MFFgsZOgAAAA=="]]}, 37], [{"py/object": "datetime.datetime", "__reduce__": [{"py/type": "datetime.datetime"}, ["B+MFFgscHgAAAA=="]]}, 36.92], [{"py/object": "datetime.datetime", "__reduce__": [{"py/type": "datetime.datetime"}, ["B+MFFgsdAgAAAA=="]]}, 37.18], [{"py/object": "datetime.datetime", "__reduce__": [{"py/type": "datetime.datetime"}, ["B+MFFgsiEwAAAA=="]]}, 37.18], [{"py/object": "datetime.datetime", "__reduce__": [{"py/type": "datetime.datetime"}, ["B+MFFgskLwAAAA=="]]}, 37.16], [{"py/object": "datetime.datetime", "__reduce__": [{"py/type": "datetime.datetime"}, ["B+MFFgsqFAAAAA=="]]}, 37.16], [{"py/object": "datetime.datetime", "__reduce__": [{"py/type": "datetime.datetime"}, ["B+MFFgsrHwAAAA=="]]}, 37.16], [{"py/object": "datetime.datetime", "__reduce__": [{"py/type": "datetime.datetime"}, ["B+MFFgsuNAAAAA=="]]}, 37.18], [{"py/object": "datetime.datetime", "__reduce__": [{"py/type": "datetime.datetime"}, ["B+MFFgswGQAAAA=="]]}, 37.14], [{"py/object": "datetime.datetime", "__reduce__": [{"py/type": "datetime.datetime"}, ["B+MFFgs0FwAAAA=="]]}, 37.18], [{"py/object": "datetime.datetime", "__reduce__": [{"py/type": "datetime.datetime"}, ["B+MFFgs1LgAAAA=="]]}, 37.3], [{"py/object": "datetime.datetime", "__reduce__": [{"py/type": "datetime.datetime"}, ["B+MFFgs4BAAAAA=="]]}, 37.3], [{"py/object": "datetime.datetime", "__reduce__": [{"py/type": "datetime.datetime"}, ["B+MFFgs5LwAAAA=="]]}, 37.4], [{"py/object": "datetime.datetime", "__reduce__": [{"py/type": "datetime.datetime"}, ["B+MFFgwBOAAAAA=="]]}, 37.2], [{"py/object": "datetime.datetime", "__reduce__": [{"py/type": "datetime.datetime"}, ["B+MFFgwDIQAAAA=="]]}, 37.36], [{"py/object": "datetime.datetime", "__reduce__": [{"py/type": "datetime.datetime"}, ["B+MFFgwIKgAAAA=="]]}, 37.36], [{"py/object": "datetime.datetime", "__reduce__": [{"py/type": "datetime.datetime"}, ["B+MFFgwLIAAAAA=="]]}, 37.38], [{"py/object": "datetime.datetime", "__reduce__": [{"py/type": "datetime.datetime"}, ["B+MFFgwOBAAAAA=="]]}, 37.4], [{"py/object": "datetime.datetime", "__reduce__": [{"py/type": "datetime.datetime"}, ["B+MFFgwPNgAAAA=="]]}, 37.4], [{"py/object": "datetime.datetime", "__reduce__": [{"py/type": "datetime.datetime"}, ["B+MFFgwSBgAAAA=="]]}, 37.78], [{"py/object": "datetime.datetime", "__reduce__": [{"py/type": "datetime.datetime"}, ["B+MFFgwUCwAAAA=="]]}, 37.76], [{"py/object": "datetime.datetime", "__reduce__": [{"py/type": "datetime.datetime"}, ["B+MFFgwWMgAAAA=="]]}, 37.76], [{"py/object": "datetime.datetime", "__reduce__": [{"py/type": "datetime.datetime"}, ["B+MFFgwYOgAAAA=="]]}, 37.7], [{"py/object": "datetime.datetime", "__reduce__": [{"py/type": "datetime.datetime"}, ["B+MFFgwcFQAAAA=="]]}, 37.8], [{"py/object": "datetime.datetime", "__reduce__": [{"py/type": "datetime.datetime"}, ["B+MFFgwgIAAAAA=="]]}, 37.4], [{"py/object": "datetime.datetime", "__reduce__": [{"py/type": "datetime.datetime"}, ["B+MFFgwhCQAAAA=="]]}, 37.54], [{"py/object": "datetime.datetime", "__reduce__": [{"py/type": "datetime.datetime"}, ["B+MFFgwkNQAAAA=="]]}, 37.54], [{"py/object": "datetime.datetime", "__reduce__": [{"py/type": "datetime.datetime"}, ["B+MFFgwsEgAAAA=="]]}, 37.78], [{"py/object": "datetime.datetime", "__reduce__": [{"py/type": "datetime.datetime"}, ["B+MFFgwuGQAAAA=="]]}, 37.74], [{"py/object": "datetime.datetime", "__reduce__": [{"py/type": "datetime.datetime"}, ["B+MFFgwwNwAAAA=="]]}, 37.74], [{"py/object": "datetime.datetime", "__reduce__": [{"py/type": "datetime.datetime"}, ["B+MFFgwyBAAAAA=="]]}, 37.78], [{"py/object": "datetime.datetime", "__reduce__": [{"py/type": "datetime.datetime"}, ["B+MFFgw0LAAAAA=="]]}, 37.78], [{"py/object": "datetime.datetime", "__reduce__": [{"py/type": "datetime.datetime"}, ["B+MFFgw4MAAAAA=="]]}, 37.78], [{"py/object": "datetime.datetime", "__reduce__": [{"py/type": "datetime.datetime"}, ["B+MFFgw6CgAAAA=="]]}, 37.74], [{"py/object": "datetime.datetime", "__reduce__": [{"py/type": "datetime.datetime"}, ["B+MFFg0BAQAAAA=="]]}, 37.76], [{"py/object": "datetime.datetime", "__reduce__": [{"py/type": "datetime.datetime"}, ["B+MFFg0DMQAAAA=="]]}, 37.76], [{"py/object": "datetime.datetime", "__reduce__": [{"py/type": "datetime.datetime"}, ["B+MFFg0GLwAAAA=="]]}, 37.64], [{"py/object": "datetime.datetime", "__reduce__": [{"py/type": "datetime.datetime"}, ["B+MFFg0JJQAAAA=="]]}, 37.64], [{"py/object": "datetime.datetime", "__reduce__": [{"py/type": "datetime.datetime"}, ["B+MFFg0MNAAAAA=="]]}, 37.7], [{"py/object": "datetime.datetime", "__reduce__": [{"py/type": "datetime.datetime"}, ["B+MFFg0ONQAAAA=="]]}, 37.7], [{"py/object": "datetime.datetime", "__reduce__": [{"py/type": "datetime.datetime"}, ["B+MFFg0SLQAAAA=="]]}, 37.74], [{"py/object": "datetime.datetime", "__reduce__": [{"py/type": "datetime.datetime"}, ["B+MFFg0UEwAAAA=="]]}, 37.76], [{"py/object": "datetime.datetime", "__reduce__": [{"py/type": "datetime.datetime"}, ["B+MFFg0VHAAAAA=="]]}, 37.94], [{"py/object": "datetime.datetime", "__reduce__": [{"py/type": "datetime.datetime"}, ["B+MFFg0XNQAAAA=="]]}, 37.98], [{"py/object": "datetime.datetime", "__reduce__": [{"py/type": "datetime.datetime"}, ["B+MFFg0aGQAAAA=="]]}, 37.98], [{"py/object": "datetime.datetime", "__reduce__": [{"py/type": "datetime.datetime"}, ["B+MFFg0cMAAAAA=="]]}, 38.5], [{"py/object": "datetime.datetime", "__reduce__": [{"py/type": "datetime.datetime"}, ["B+MFFg0dAwAAAA=="]]}, 38.34], [{"py/object": "datetime.datetime", "__reduce__": [{"py/type": "datetime.datetime"}, ["B+MFFg0fLAAAAA=="]]}, 38.5], [{"py/object": "datetime.datetime", "__reduce__": [{"py/type": "datetime.datetime"}, ["B+MFFg0iKAAAAA=="]]}, 38.54], [{"py/object": "datetime.datetime", "__reduce__": [{"py/type": "datetime.datetime"}, ["B+MFFg0kLQAAAA=="]]}, 38.34], [{"py/object": "datetime.datetime", "__reduce__": [{"py/type": "datetime.datetime"}, ["B+MFFg0mEgAAAA=="]]}, 38.5], [{"py/object": "datetime.datetime", "__reduce__": [{"py/type": "datetime.datetime"}, ["B+MFFg0oHQAAAA=="]]}, 38.42], [{"py/object": "datetime.datetime", "__reduce__": [{"py/type": "datetime.datetime"}, ["B+MFFg0pNwAAAA=="]]}, 38.42], [{"py/object": "datetime.datetime", "__reduce__": [{"py/type": "datetime.datetime"}, ["B+MFFg0sNAAAAA=="]]}, 38.34], [{"py/object": "datetime.datetime", "__reduce__": [{"py/type": "datetime.datetime"}, ["B+MFFg0wNwAAAA=="]]}, 38.5], [{"py/object": "datetime.datetime", "__reduce__": [{"py/type": "datetime.datetime"}, ["B+MFFg0xKQAAAA=="]]}, 38.56], [{"py/object": "datetime.datetime", "__reduce__": [{"py/type": "datetime.datetime"}, ["B+MFFg02GgAAAA=="]]}, 38.5], [{"py/object": "datetime.datetime", "__reduce__": [{"py/type": "datetime.datetime"}, ["B+MFFg04JwAAAA=="]]}, 38.7], [{"py/object": "datetime.datetime", "__reduce__": [{"py/type": "datetime.datetime"}, ["B+MFFg06LwAAAA=="]]}, 38.74], [{"py/object": "datetime.datetime", "__reduce__": [{"py/type": "datetime.datetime"}, ["B+MFFg4AHAAAAA=="]]}, 38.74], [{"py/object": "datetime.datetime", "__reduce__": [{"py/type": "datetime.datetime"}, ["B+MFFg4BJgAAAA=="]]}, 38.8], [{"py/object": "datetime.datetime", "__reduce__": [{"py/type": "datetime.datetime"}, ["B+MFFg4EHgAAAA=="]]}, 38.78], [{"py/object": "datetime.datetime", "__reduce__": [{"py/type": "datetime.datetime"}, ["B+MFFg4GKgAAAA=="]]}, 38.6], [{"py/object": "datetime.datetime", "__reduce__": [{"py/type": "datetime.datetime"}, ["B+MFFg4INgAAAA=="]]}, 38.7], [{"py/object": "datetime.datetime", "__reduce__": [{"py/type": "datetime.datetime"}, ["B+MFFg4KLwAAAA=="]]}, 38.34], [{"py/object": "datetime.datetime", "__reduce__": [{"py/type": "datetime.datetime"}, ["B+MFFg4LOAAAAA=="]]}, 38.5], [{"py/object": "datetime.datetime", "__reduce__": [{"py/type": "datetime.datetime"}, ["B+MFFg4OEwAAAA=="]]}, 38.5], [{"py/object": "datetime.datetime", "__reduce__": [{"py/type": "datetime.datetime"}, ["B+MFFg4QKgAAAA=="]]}, 38.36], [{"py/object": "datetime.datetime", "__reduce__": [{"py/type": "datetime.datetime"}, ["B+MFFg4SCwAAAA=="]]}, 38.52], [{"py/object": "datetime.datetime", "__reduce__": [{"py/type": "datetime.datetime"}, ["B+MFFg4UOAAAAA=="]]}, 38.58], [{"py/object": "datetime.datetime", "__reduce__": [{"py/type": "datetime.datetime"}, ["B+MFFg4cJQAAAA=="]]}, 38.66], [{"py/object": "datetime.datetime", "__reduce__": [{"py/type": "datetime.datetime"}, ["B+MFFg4hHAAAAA=="]]}, 38.7], [{"py/object": "datetime.datetime", "__reduce__": [{"py/type": "datetime.datetime"}, ["B+MFFg4lFAAAAA=="]]}, 38.68], [{"py/object": "datetime.datetime", "__reduce__": [{"py/type": "datetime.datetime"}, ["B+MFFg4qJgAAAA=="]]}, 38.66], [{"py/object": "datetime.datetime", "__reduce__": [{"py/type": "datetime.datetime"}, ["B+MFFg44MwAAAA=="]]}, 38.68], [{"py/object": "datetime.datetime", "__reduce__": [{"py/type": "datetime.datetime"}, ["B+MFFg8AMwAAAA=="]]}, 38.68], [{"py/object": "datetime.datetime", "__reduce__": [{"py/type": "datetime.datetime"}, ["B+MFFg8HMwAAAA=="]]}, 38.6], [{"py/object": "datetime.datetime", "__reduce__": [{"py/type": "datetime.datetime"}, ["B+MFFg8JCwAAAA=="]]}, 38.56], [{"py/object": "datetime.datetime", "__reduce__": [{"py/type": "datetime.datetime"}, ["B+MFFg8UBwAAAA=="]]}, 38.24], [{"py/object": "datetime.datetime", "__reduce__": [{"py/type": "datetime.datetime"}, ["B+MFFg8YOgAAAA=="]]}, 38.34], [{"py/object": "datetime.datetime", "__reduce__": [{"py/type": "datetime.datetime"}, ["B+MFFg8aLgAAAA=="]]}, 38.08], [{"py/object": "datetime.datetime", "__reduce__": [{"py/type": "datetime.datetime"}, ["B+MFFg8bEAAAAA=="]]}, 37.88], [{"py/object": "datetime.datetime", "__reduce__": [{"py/type": "datetime.datetime"}, ["B+MFFg8dEgAAAA=="]]}, 37.96], [{"py/object": "datetime.datetime", "__reduce__": [{"py/type": "datetime.datetime"}, ["B+MFFg8jMwAAAA=="]]}, 37.88], [{"py/object": "datetime.datetime", "__reduce__": [{"py/type": "datetime.datetime"}, ["B+MFFg8mKwAAAA=="]]}, 37.8], [{"py/object": "datetime.datetime", "__reduce__": [{"py/type": "datetime.datetime"}, ["B+MFFg8oKwAAAA=="]]}, 37.6], [{"py/object": "datetime.datetime", "__reduce__": [{"py/type": "datetime.datetime"}, ["B+MFFg8qEgAAAA=="]]}, 37.5], [{"py/object": "datetime.datetime", "__reduce__": [{"py/type": "datetime.datetime"}, ["B+MFFg8vFAAAAA=="]]}, 37.5], [{"py/object": "datetime.datetime", "__reduce__": [{"py/type": "datetime.datetime"}, ["B+MFFg8yIQAAAA=="]]}, 37.54], [{"py/object": "datetime.datetime", "__reduce__": [{"py/type": "datetime.datetime"}, ["B+MFFg80OQAAAA=="]]}, 37.54], [{"py/object": "datetime.datetime", "__reduce__": [{"py/type": "datetime.datetime"}, ["B+MFFg81DwAAAA=="]]}, 37.46], [{"py/object": "datetime.datetime", "__reduce__": [{"py/type": "datetime.datetime"}, ["B+MFFg86LwAAAA=="]]}, 37.5], [{"py/object": "datetime.datetime", "__reduce__": [{"py/type": "datetime.datetime"}, ["B+MFFg87IQAAAA=="]]}, 37.5], [{"py/object": "datetime.datetime", "__reduce__": [{"py/type": "datetime.datetime"}, ["B+MFFhACOgAAAA=="]]}, 37.64], [{"py/object": "datetime.datetime", "__reduce__": [{"py/type": "datetime.datetime"}, ["B+MFFhAELgAAAA=="]]}, 37.64], [{"py/object": "datetime.datetime", "__reduce__": [{"py/type": "datetime.datetime"}, ["B+MFFhAGGQAAAA=="]]}, 37.5], [{"py/object": "datetime.datetime", "__reduce__": [{"py/type": "datetime.datetime"}, ["B+MFFhAHNQAAAA=="]]}, 37.5], [{"py/object": "datetime.datetime", "__reduce__": [{"py/type": "datetime.datetime"}, ["B+MFFhAMGQAAAA=="]]}, 37.56], [{"py/object": "datetime.datetime", "__reduce__": [{"py/type": "datetime.datetime"}, ["B+MFFhAOHwAAAA=="]]}, 37.46], [{"py/object": "datetime.datetime", "__reduce__": [{"py/type": "datetime.datetime"}, ["B+MFFhATJQAAAA=="]]}, 37.58], [{"py/object": "datetime.datetime", "__reduce__": [{"py/type": "datetime.datetime"}, ["B+MFFhAVDAAAAA=="]]}, 37.48], [{"py/object": "datetime.datetime", "__reduce__": [{"py/type": "datetime.datetime"}, ["B+MFFhAZFgAAAA=="]]}, 37.58], [{"py/object": "datetime.datetime", "__reduce__": [{"py/type": "datetime.datetime"}, ["B+MFFhAcIgAAAA=="]]}, 37.48], [{"py/object": "datetime.datetime", "__reduce__": [{"py/type": "datetime.datetime"}, ["B+MFFhAhHwAAAA=="]]}, 37.48], [{"py/object": "datetime.datetime", "__reduce__": [{"py/type": "datetime.datetime"}, ["B+MFFhAkMgAAAA=="]]}, 37.52], [{"py/object": "datetime.datetime", "__reduce__": [{"py/type": "datetime.datetime"}, ["B+MFFhAqNAAAAA=="]]}, 37.48], [{"py/object": "datetime.datetime", "__reduce__": [{"py/type": "datetime.datetime"}, ["B+MFFhArOQAAAA=="]]}, 37.46], [{"py/object": "datetime.datetime", "__reduce__": [{"py/type": "datetime.datetime"}, ["B+MFFhAvJQAAAA=="]]}, 37.54], [{"py/object": "datetime.datetime", "__reduce__": [{"py/type": "datetime.datetime"}, ["B+MFFhAyNAAAAA=="]]}, 37.5], [{"py/object": "datetime.datetime", "__reduce__": [{"py/type": "datetime.datetime"}, ["B+MFFhA0HQAAAA=="]]}, 37.5], [{"py/object": "datetime.datetime", "__reduce__": [{"py/type": "datetime.datetime"}, ["B+MFFhA2CAAAAA=="]]}, 37.48], [{"py/object": "datetime.datetime", "__reduce__": [{"py/type": "datetime.datetime"}, ["B+MFFhA4HAAAAA=="]]}, 37.48], [{"py/object": "datetime.datetime", "__reduce__": [{"py/type": "datetime.datetime"}, ["B+MFFhA6DQAAAA=="]]}, 37.48], [{"py/object": "datetime.datetime", "__reduce__": [{"py/type": "datetime.datetime"}, ["B+MFFhEALgAAAA=="]]}, 37.5], [{"py/object": "datetime.datetime", "__reduce__": [{"py/type": "datetime.datetime"}, ["B+MFFhEBLwAAAA=="]]}, 37.5], [{"py/object": "datetime.datetime", "__reduce__": [{"py/type": "datetime.datetime"}, ["B+MFFhEELwAAAA=="]]}, 37.5], [{"py/object": "datetime.datetime", "__reduce__": [{"py/type": "datetime.datetime"}, ["B+MFFhEGBQAAAA=="]]}, 37.48], [{"py/object": "datetime.datetime", "__reduce__": [{"py/type": "datetime.datetime"}, ["B+MFFhEHJAAAAA=="]]}, 37.48], [{"py/object": "datetime.datetime", "__reduce__": [{"py/type": "datetime.datetime"}, ["B+MFFhELCwAAAA=="]]}, 37.46], [{"py/object": "datetime.datetime", "__reduce__": [{"py/type": "datetime.datetime"}, ["B+MFFhENHQAAAA=="]]}, 37.5], [{"py/object": "datetime.datetime", "__reduce__": [{"py/type": "datetime.datetime"}, ["B+MFFhERFgAAAA=="]]}, 37.5], [{"py/object": "datetime.datetime", "__reduce__": [{"py/type": "datetime.datetime"}, ["B+MFFhEUEgAAAA=="]]}, 37.54], [{"py/object": "datetime.datetime", "__reduce__": [{"py/type": "datetime.datetime"}, ["B+MFFhEVAwAAAA=="]]}, 37.6], [{"py/object": "datetime.datetime", "__reduce__": [{"py/type": "datetime.datetime"}, ["B+MFFhEeMwAAAA=="]]}, 37.48], [{"py/object": "datetime.datetime", "__reduce__": [{"py/type": "datetime.datetime"}, ["B+MFFhEgNQAAAA=="]]}, 37.5], [{"py/object": "datetime.datetime", "__reduce__": [{"py/type": "datetime.datetime"}, ["B+MFFhEkMwAAAA=="]]}, 37.5], [{"py/object": "datetime.datetime", "__reduce__": [{"py/type": "datetime.datetime"}, ["B+MFFhEmFAAAAA=="]]}, 37.54], [{"py/object": "datetime.datetime", "__reduce__": [{"py/type": "datetime.datetime"}, ["B+MFFhEpDAAAAA=="]]}, 37.56], [{"py/object": "datetime.datetime", "__reduce__": [{"py/type": "datetime.datetime"}, ["B+MFFhEyNQAAAA=="]]}, 37.58], [{"py/object": "datetime.datetime", "__reduce__": [{"py/type": "datetime.datetime"}, ["B+MFFhE1HwAAAA=="]]}, 37.62], [{"py/object": "datetime.datetime", "__reduce__": [{"py/type": "datetime.datetime"}, ["B+MFFhE6EAAAAA=="]]}, 37.62], [{"py/object": "datetime.datetime", "__reduce__": [{"py/type": "datetime.datetime"}, ["B+MFFhIAFgAAAA=="]]}, 37.64], [{"py/object": "datetime.datetime", "__reduce__": [{"py/type": "datetime.datetime"}, ["B+MFFhIDEwAAAA=="]]}, 37.64], [{"py/object": "datetime.datetime", "__reduce__": [{"py/type": "datetime.datetime"}, ["B+MFFhIFBAAAAA=="]]}, 37.64], [{"py/object": "datetime.datetime", "__reduce__": [{"py/type": "datetime.datetime"}, ["B+MFFhIHJAAAAA=="]]}, 37.7], [{"py/object": "datetime.datetime", "__reduce__": [{"py/type": "datetime.datetime"}, ["B+MFFhIKEwAAAA=="]]}, 37.68], [{"py/object": "datetime.datetime", "__reduce__": [{"py/type": "datetime.datetime"}, ["B+MFFhIMCQAAAA=="]]}, 37.76], [{"py/object": "datetime.datetime", "__reduce__": [{"py/type": "datetime.datetime"}, ["B+MFFhIOAwAAAA=="]]}, 37.76], [{"py/object": "datetime.datetime", "__reduce__": [{"py/type": "datetime.datetime"}, ["B+MFFhIUDwAAAA=="]]}, 37.76], [{"py/object": "datetime.datetime", "__reduce__": [{"py/type": "datetime.datetime"}, ["B+MFFhIVOQAAAA=="]]}, 37.64], [{"py/object": "datetime.datetime", "__reduce__": [{"py/type": "datetime.datetime"}, ["B+MFFhIYHgAAAA=="]]}, 37.66], [{"py/object": "datetime.datetime", "__reduce__": [{"py/type": "datetime.datetime"}, ["B+MFFhIZOwAAAA=="]]}, 37.66], [{"py/object": "datetime.datetime", "__reduce__": [{"py/type": "datetime.datetime"}, ["B+MFFhIcLgAAAA=="]]}, 37.84], [{"py/object": "datetime.datetime", "__reduce__": [{"py/type": "datetime.datetime"}, ["B+MFFhIfHwAAAA=="]]}, 37.76], [{"py/object": "datetime.datetime", "__reduce__": [{"py/type": "datetime.datetime"}, ["B+MFFhIkNwAAAA=="]]}, 37.96], [{"py/object": "datetime.datetime", "__reduce__": [{"py/type": "datetime.datetime"}, ["B+MFFhIlBAAAAA=="]]}, 37.96], [{"py/object": "datetime.datetime", "__reduce__": [{"py/type": "datetime.datetime"}, ["B+MFFhInJAAAAA=="]]}, 37.94], [{"py/object": "datetime.datetime", "__reduce__": [{"py/type": "datetime.datetime"}, ["B+MFFhIpAgAAAA=="]]}, 37.94], [{"py/object": "datetime.datetime", "__reduce__": [{"py/type": "datetime.datetime"}, ["B+MFFhIsGQAAAA=="]]}, 37.96], [{"py/object": "datetime.datetime", "__reduce__": [{"py/type": "datetime.datetime"}, ["B+MFFhIuKwAAAA=="]]}, 37.64], [{"py/object": "datetime.datetime", "__reduce__": [{"py/type": "datetime.datetime"}, ["B+MFFhIvLgAAAA=="]]}, 37.5], [{"py/object": "datetime.datetime", "__reduce__": [{"py/type": "datetime.datetime"}, ["B+MFFhIxMAAAAA=="]]}, 37.86], [{"py/object": "datetime.datetime", "__reduce__": [{"py/type": "datetime.datetime"}, ["B+MFFhMABgAAAA=="]]}, 37.8], [{"py/object": "datetime.datetime", "__reduce__": [{"py/type": "datetime.datetime"}, ["B+MFFhMCHwAAAA=="]]}, 37.8], [{"py/object": "datetime.datetime", "__reduce__": [{"py/type": "datetime.datetime"}, ["B+MFFhMEAwAAAA=="]]}, 37.8], [{"py/object": "datetime.datetime", "__reduce__": [{"py/type": "datetime.datetime"}, ["B+MFFwsAMQAAAA=="]]}, 38.92], [{"py/object": "datetime.datetime", "__reduce__": [{"py/type": "datetime.datetime"}, ["B+MFFwsCKQAAAA=="]]}, 38.64], [{"py/object": "datetime.datetime", "__reduce__": [{"py/type": "datetime.datetime"}, ["B+MFFwsEHAAAAA=="]]}, 39.1], [{"py/object": "datetime.datetime", "__reduce__": [{"py/type": "datetime.datetime"}, ["B+MFFwsFIgAAAA=="]]}, 39], [{"py/object": "datetime.datetime", "__reduce__": [{"py/type": "datetime.datetime"}, ["B+MFFwsIHwAAAA=="]]}, 38.98], [{"py/object": "datetime.datetime", "__reduce__": [{"py/type": "datetime.datetime"}, ["B+MFFwsKNQAAAA=="]]}, 38.9], [{"py/object": "datetime.datetime", "__reduce__": [{"py/type": "datetime.datetime"}, ["B+MFFwsMGQAAAA=="]]}, 38.5], [{"py/object": "datetime.datetime", "__reduce__": [{"py/type": "datetime.datetime"}, ["B+MFFwsOFAAAAA=="]]}, 38.56], [{"py/object": "datetime.datetime", "__reduce__": [{"py/type": "datetime.datetime"}, ["B+MFFwsQFwAAAA=="]]}, 38.52], [{"py/object": "datetime.datetime", "__reduce__": [{"py/type": "datetime.datetime"}, ["B+MFFwsSJAAAAA=="]]}, 37.8], [{"py/object": "datetime.datetime", "__reduce__": [{"py/type": "datetime.datetime"}, ["B+MFFwsUCQAAAA=="]]}, 38], [{"py/object": "datetime.datetime", "__reduce__": [{"py/type": "datetime.datetime"}, ["B+MFFwsWBgAAAA=="]]}, 38.26], [{"py/object": "datetime.datetime", "__reduce__": [{"py/type": "datetime.datetime"}, ["B+MFFwsYJgAAAA=="]]}, 38.4], [{"py/object": "datetime.datetime", "__reduce__": [{"py/type": "datetime.datetime"}, ["B+MFFwsZOwAAAA=="]]}, 38.66], [{"py/object": "datetime.datetime", "__reduce__": [{"py/type": "datetime.datetime"}, ["B+MFFwscCwAAAA=="]]}, 38.5], [{"py/object": "datetime.datetime", "__reduce__": [{"py/type": "datetime.datetime"}, ["B+MFFwseNAAAAA=="]]}, 38.2], [{"py/object": "datetime.datetime", "__reduce__": [{"py/type": "datetime.datetime"}, ["B+MFFwsgNAAAAA=="]]}, 38.1], [{"py/object": "datetime.datetime", "__reduce__": [{"py/type": "datetime.datetime"}, ["B+MFFwsiEwAAAA=="]]}, 38.1], [{"py/object": "datetime.datetime", "__reduce__": [{"py/type": "datetime.datetime"}, ["B+MFFwskBgAAAA=="]]}, 38.1], [{"py/object": "datetime.datetime", "__reduce__": [{"py/type": "datetime.datetime"}, ["B+MFFwsmFAAAAA=="]]}, 38.1], [{"py/object": "datetime.datetime", "__reduce__": [{"py/type": "datetime.datetime"}, ["B+MFFwsoGwAAAA=="]]}, 38.14], [{"py/object": "datetime.datetime", "__reduce__": [{"py/type": "datetime.datetime"}, ["B+MFFwspDwAAAA=="]]}, 38.1], [{"py/object": "datetime.datetime", "__reduce__": [{"py/type": "datetime.datetime"}, ["B+MFFwssJwAAAA=="]]}, 38.1], [{"py/object": "datetime.datetime", "__reduce__": [{"py/type": "datetime.datetime"}, ["B+MFFws6CgAAAA=="]]}, 38.12], [{"py/object": "datetime.datetime", "__reduce__": [{"py/type": "datetime.datetime"}, ["B+MFFws7JQAAAA=="]]}, 38.12], [{"py/object": "datetime.datetime", "__reduce__": [{"py/type": "datetime.datetime"}, ["B+MFFwwCGwAAAA=="]]}, 38.12], [{"py/object": "datetime.datetime", "__reduce__": [{"py/type": "datetime.datetime"}, ["B+MFFwwEEQAAAA=="]]}, 38.12], [{"py/object": "datetime.datetime", "__reduce__": [{"py/type": "datetime.datetime"}, ["B+MFFwwGOQAAAA=="]]}, 38.1], [{"py/object": "datetime.datetime", "__reduce__": [{"py/type": "datetime.datetime"}, ["B+MFFwwHEAAAAA=="]]}, 38], [{"py/object": "datetime.datetime", "__reduce__": [{"py/type": "datetime.datetime"}, ["B+MFFwwKEwAAAA=="]]}, 38], [{"py/object": "datetime.datetime", "__reduce__": [{"py/type": "datetime.datetime"}, ["B+MFFwwMHwAAAA=="]]}, 38.1], [{"py/object": "datetime.datetime", "__reduce__": [{"py/type": "datetime.datetime"}, ["B+MFFwwNOAAAAA=="]]}, 38.1], [{"py/object": "datetime.datetime", "__reduce__": [{"py/type": "datetime.datetime"}, ["B+MFFwwQJAAAAA=="]]}, 38.2], [{"py/object": "datetime.datetime", "__reduce__": [{"py/type": "datetime.datetime"}, ["B+MFFwwSMgAAAA=="]]}, 38.2], [{"py/object": "datetime.datetime", "__reduce__": [{"py/type": "datetime.datetime"}, ["B+MFFwwVKAAAAA=="]]}, 38.2], [{"py/object": "datetime.datetime", "__reduce__": [{"py/type": "datetime.datetime"}, ["B+MFFwwYIwAAAA=="]]}, 38.16], [{"py/object": "datetime.datetime", "__reduce__": [{"py/type": "datetime.datetime"}, ["B+MFFwwbNgAAAA=="]]}, 38], [{"py/object": "datetime.datetime", "__reduce__": [{"py/type": "datetime.datetime"}, ["B+MFFwwgJgAAAA=="]]}, 38], [{"py/object": "datetime.datetime", "__reduce__": [{"py/type": "datetime.datetime"}, ["B+MFFwwiBQAAAA=="]]}, 38], [{"py/object": "datetime.datetime", "__reduce__": [{"py/type": "datetime.datetime"}, ["B+MFFwwjIQAAAA=="]]}, 38.2], [{"py/object": "datetime.datetime", "__reduce__": [{"py/type": "datetime.datetime"}, ["B+MFFwwnLAAAAA=="]]}, 38], [{"py/object": "datetime.datetime", "__reduce__": [{"py/type": "datetime.datetime"}, ["B+MFFwwqLQAAAA=="]]}, 38.4], [{"py/object": "datetime.datetime", "__reduce__": [{"py/type": "datetime.datetime"}, ["B+MFFwwrOAAAAA=="]]}, 38.5], [{"py/object": "datetime.datetime", "__reduce__": [{"py/type": "datetime.datetime"}, ["B+MFFwwwHAAAAA=="]]}, 38.42], [{"py/object": "datetime.datetime", "__reduce__": [{"py/type": "datetime.datetime"}, ["B+MFFwwxOQAAAA=="]]}, 38.42], [{"py/object": "datetime.datetime", "__reduce__": [{"py/type": "datetime.datetime"}, ["B+MFFww0AQAAAA=="]]}, 38.5], [{"py/object": "datetime.datetime", "__reduce__": [{"py/type": "datetime.datetime"}, ["B+MFFww2KAAAAA=="]]}, 38.5], [{"py/object": "datetime.datetime", "__reduce__": [{"py/type": "datetime.datetime"}, ["B+MFFww3JgAAAA=="]]}, 38.58], [{"py/object": "datetime.datetime", "__reduce__": [{"py/type": "datetime.datetime"}, ["B+MFFw0CDQAAAA=="]]}, 38.42], [{"py/object": "datetime.datetime", "__reduce__": [{"py/type": "datetime.datetime"}, ["B+MFFw0LHgAAAA=="]]}, 38.5], [{"py/object": "datetime.datetime", "__reduce__": [{"py/type": "datetime.datetime"}, ["B+MFFw0UMwAAAA=="]]}, 38.5], [{"py/object": "datetime.datetime", "__reduce__": [{"py/type": "datetime.datetime"}, ["B+MFFw0YMgAAAA=="]]}, 38.56], [{"py/object": "datetime.datetime", "__reduce__": [{"py/type": "datetime.datetime"}, ["B+MFFw0cMQAAAA=="]]}, 38.5], [{"py/object": "datetime.datetime", "__reduce__": [{"py/type": "datetime.datetime"}, ["B+MFFw0fKgAAAA=="]]}, 38.56], [{"py/object": "datetime.datetime", "__reduce__": [{"py/type": "datetime.datetime"}, ["B+MFFw0kCQAAAA=="]]}, 38.52], [{"py/object": "datetime.datetime", "__reduce__": [{"py/type": "datetime.datetime"}, ["B+MFFw0oDAAAAA=="]]}, 38.56], [{"py/object": "datetime.datetime", "__reduce__": [{"py/type": "datetime.datetime"}, ["B+MFFw0qDgAAAA=="]]}, 38.5], [{"py/object": "datetime.datetime", "__reduce__": [{"py/type": "datetime.datetime"}, ["B+MFFw0rKgAAAA=="]]}, 38.56], [{"py/object": "datetime.datetime", "__reduce__": [{"py/type": "datetime.datetime"}, ["B+MFFw04GQAAAA=="]]}, 38.5], [{"py/object": "datetime.datetime", "__reduce__": [{"py/type": "datetime.datetime"}, ["B+MFFw05KQAAAA=="]]}, 38.56], [{"py/object": "datetime.datetime", "__reduce__": [{"py/type": "datetime.datetime"}, ["B+MFFw4ANwAAAA=="]]}, 38.82], [{"py/object": "datetime.datetime", "__reduce__": [{"py/type": "datetime.datetime"}, ["B+MFFw4DGAAAAA=="]]}, 38.8], [{"py/object": "datetime.datetime", "__reduce__": [{"py/type": "datetime.datetime"}, ["B+MFFw4FOQAAAA=="]]}, 38.8], [{"py/object": "datetime.datetime", "__reduce__": [{"py/type": "datetime.datetime"}, ["B+MFFw4HHQAAAA=="]]}, 38.8], [{"py/object": "datetime.datetime", "__reduce__": [{"py/type": "datetime.datetime"}, ["B+MFFw4NEwAAAA=="]]}, 38.7], [{"py/object": "datetime.datetime", "__reduce__": [{"py/type": "datetime.datetime"}, ["B+MFFw4SDAAAAA=="]]}, 38.7], [{"py/object": "datetime.datetime", "__reduce__": [{"py/type": "datetime.datetime"}, ["B+MFFw4cBQAAAA=="]]}, 38.72], [{"py/object": "datetime.datetime", "__reduce__": [{"py/type": "datetime.datetime"}, ["B+MFFw4gMgAAAA=="]]}, 38.68], [{"py/object": "datetime.datetime", "__reduce__": [{"py/type": "datetime.datetime"}, ["B+MFFw4hEwAAAA=="]]}, 38.66], [{"py/object": "datetime.datetime", "__reduce__": [{"py/type": "datetime.datetime"}, ["B+MFFw4jHQAAAA=="]]}, 38.64], [{"py/object": "datetime.datetime", "__reduce__": [{"py/type": "datetime.datetime"}, ["B+MFFw4uMAAAAA=="]]}, 38.66], [{"py/object": "datetime.datetime", "__reduce__": [{"py/type": "datetime.datetime"}, ["B+MFFw4yIQAAAA=="]]}, 38.66], [{"py/object": "datetime.datetime", "__reduce__": [{"py/type": "datetime.datetime"}, ["B+MFFw8EDwAAAA=="]]}, 38.56], [{"py/object": "datetime.datetime", "__reduce__": [{"py/type": "datetime.datetime"}, ["B+MFFw8FIAAAAA=="]]}, 38.5], [{"py/object": "datetime.datetime", "__reduce__": [{"py/type": "datetime.datetime"}, ["B+MFFw8JFAAAAA=="]]}, 38.5], [{"py/object": "datetime.datetime", "__reduce__": [{"py/type": "datetime.datetime"}, ["B+MFFw8OGQAAAA=="]]}, 38.62], [{"py/object": "datetime.datetime", "__reduce__": [{"py/type": "datetime.datetime"}, ["B+MFFw8SAwAAAA=="]]}, 38.6], [{"py/object": "datetime.datetime", "__reduce__": [{"py/type": "datetime.datetime"}, ["B+MFFw8pMAAAAA=="]]}, 38.5], [{"py/object": "datetime.datetime", "__reduce__": [{"py/type": "datetime.datetime"}, ["B+MFFw8uGwAAAA=="]]}, 38.6], [{"py/object": "datetime.datetime", "__reduce__": [{"py/type": "datetime.datetime"}, ["B+MFFw8xCgAAAA=="]]}, 38.5], [{"py/object": "datetime.datetime", "__reduce__": [{"py/type": "datetime.datetime"}, ["B+MFFxAAFAAAAA=="]]}, 38.44], [{"py/object": "datetime.datetime", "__reduce__": [{"py/type": "datetime.datetime"}, ["B+MFFxABJQAAAA=="]]}, 38.32], [{"py/object": "datetime.datetime", "__reduce__": [{"py/type": "datetime.datetime"}, ["B+MFFxAKFAAAAA=="]]}, 38.3], [{"py/object": "datetime.datetime", "__reduce__": [{"py/type": "datetime.datetime"}, ["B+MFFxALHAAAAA=="]]}, 38.2], [{"py/object": "datetime.datetime", "__reduce__": [{"py/type": "datetime.datetime"}, ["B+MFFxAONAAAAA=="]]}, 38.24], [{"py/object": "datetime.datetime", "__reduce__": [{"py/type": "datetime.datetime"}, ["B+MFFxATBgAAAA=="]]}, 38.3], [{"py/object": "datetime.datetime", "__reduce__": [{"py/type": "datetime.datetime"}, ["B+MFFxAYMAAAAA=="]]}, 38.3], [{"py/object": "datetime.datetime", "__reduce__": [{"py/type": "datetime.datetime"}, ["B+MFFxAZGgAAAA=="]]}, 38.3], [{"py/object": "datetime.datetime", "__reduce__": [{"py/type": "datetime.datetime"}, ["B+MFFxAeCgAAAA=="]]}, 38.3], [{"py/object": "datetime.datetime", "__reduce__": [{"py/type": "datetime.datetime"}, ["B+MFFxAhFAAAAA=="]]}, 38.3], [{"py/object": "datetime.datetime", "__reduce__": [{"py/type": "datetime.datetime"}, ["B+MFFxAjHgAAAA=="]]}, 38.3], [{"py/object": "datetime.datetime", "__reduce__": [{"py/type": "datetime.datetime"}, ["B+MFFxAuAAAAAA=="]]}, 38.3], [{"py/object": "datetime.datetime", "__reduce__": [{"py/type": "datetime.datetime"}, ["B+MFFxA2OQAAAA=="]]}, 38.14], [{"py/object": "datetime.datetime", "__reduce__": [{"py/type": "datetime.datetime"}, ["B+MFFxEMKgAAAA=="]]}, 38.22], [{"py/object": "datetime.datetime", "__reduce__": [{"py/type": "datetime.datetime"}, ["B+MFFxENBQAAAA=="]]}, 38.22], [{"py/object": "datetime.datetime", "__reduce__": [{"py/type": "datetime.datetime"}, ["B+MFFxERCwAAAA=="]]}, 38.08], [{"py/object": "datetime.datetime", "__reduce__": [{"py/type": "datetime.datetime"}, ["B+MFFxEZDQAAAA=="]]}, 38.08], [{"py/object": "datetime.datetime", "__reduce__": [{"py/type": "datetime.datetime"}, ["B+MFFxEmMQAAAA=="]]}, 38.22], [{"py/object": "datetime.datetime", "__reduce__": [{"py/type": "datetime.datetime"}, ["B+MFFxEqNgAAAA=="]]}, 38.1], [{"py/object": "datetime.datetime", "__reduce__": [{"py/type": "datetime.datetime"}, ["B+MFFxEuFwAAAA=="]]}, 38], [{"py/object": "datetime.datetime", "__reduce__": [{"py/type": "datetime.datetime"}, ["B+MFFxEvOwAAAA=="]]}, 37.86], [{"py/object": "datetime.datetime", "__reduce__": [{"py/type": "datetime.datetime"}, ["B+MFFxEzGgAAAA=="]]}, 37.86], [{"py/object": "datetime.datetime", "__reduce__": [{"py/type": "datetime.datetime"}, ["B+MFFxE1JgAAAA=="]]}, 37.8], [{"py/object": "datetime.datetime", "__reduce__": [{"py/type": "datetime.datetime"}, ["B+MFFxE6JQAAAA=="]]}, 37.86], [{"py/object": "datetime.datetime", "__reduce__": [{"py/type": "datetime.datetime"}, ["B+MFFxIBKwAAAA=="]]}, 37.86], [{"py/object": "datetime.datetime", "__reduce__": [{"py/type": "datetime.datetime"}, ["B+MFFxIFJQAAAA=="]]}, 37.84], [{"py/object": "datetime.datetime", "__reduce__": [{"py/type": "datetime.datetime"}, ["B+MFFxIIOAAAAA=="]]}, 37.76], [{"py/object": "datetime.datetime", "__reduce__": [{"py/type": "datetime.datetime"}, ["B+MFFxIKCgAAAA=="]]}, 37.76], [{"py/object": "datetime.datetime", "__reduce__": [{"py/type": "datetime.datetime"}, ["B+MFFxIMMwAAAA=="]]}, 37.86], [{"py/object": "datetime.datetime", "__reduce__": [{"py/type": "datetime.datetime"}, ["B+MFFxINEwAAAA=="]]}, 37.8], [{"py/object": "datetime.datetime", "__reduce__": [{"py/type": "datetime.datetime"}, ["B+MFFxIQBgAAAA=="]]}, 37.8], [{"py/object": "datetime.datetime", "__reduce__": [{"py/type": "datetime.datetime"}, ["B+MFFxIUMgAAAA=="]]}, 37.8], [{"py/object": "datetime.datetime", "__reduce__": [{"py/type": "datetime.datetime"}, ["B+MFFxIVHwAAAA=="]]}, 37.58], [{"py/object": "datetime.datetime", "__reduce__": [{"py/type": "datetime.datetime"}, ["B+MFFxIZFgAAAA=="]]}, 37.78], [{"py/object": "datetime.datetime", "__reduce__": [{"py/type": "datetime.datetime"}, ["B+MFFxIcNQAAAA=="]]}, 37.74], [{"py/object": "datetime.datetime", "__reduce__": [{"py/type": "datetime.datetime"}, ["B+MFFxIkHwAAAA=="]]}, 37.74], [{"py/object": "datetime.datetime", "__reduce__": [{"py/type": "datetime.datetime"}, ["B+MFFxIlOwAAAA=="]]}, 37.6], [{"py/object": "datetime.datetime", "__reduce__": [{"py/type": "datetime.datetime"}, ["B+MFFxIoOAAAAA=="]]}, 37.6], [{"py/object": "datetime.datetime", "__reduce__": [{"py/type": "datetime.datetime"}, ["B+MFFxIqBgAAAA=="]]}, 37.58], [{"py/object": "datetime.datetime", "__reduce__": [{"py/type": "datetime.datetime"}, ["B+MFFxIsFAAAAA=="]]}, 37.58], [{"py/object": "datetime.datetime", "__reduce__": [{"py/type": "datetime.datetime"}, ["B+MFFxIuKwAAAA=="]]}, 37.5], [{"py/object": "datetime.datetime", "__reduce__": [{"py/type": "datetime.datetime"}, ["B+MFFxIwIwAAAA=="]]}, 37.3], [{"py/object": "datetime.datetime", "__reduce__": [{"py/type": "datetime.datetime"}, ["B+MFFxIxLwAAAA=="]]}, 36.98], [{"py/object": "datetime.datetime", "__reduce__": [{"py/type": "datetime.datetime"}, ["B+MFFxMAAAAAAA=="]]}, 37.2], [{"py/object": "datetime.datetime", "__reduce__": [{"py/type": "datetime.datetime"}, ["B+MFGAsAAAAAAA=="]]}, 37.5], [{"py/object": "datetime.datetime", "__reduce__": [{"py/type": "datetime.datetime"}, ["B+MFGAsCEwAAAA=="]]}, 37.6], [{"py/object": "datetime.datetime", "__reduce__": [{"py/type": "datetime.datetime"}, ["B+MFGAsFEwAAAA=="]]}, 37.88], [{"py/object": "datetime.datetime", "__reduce__": [{"py/type": "datetime.datetime"}, ["B+MFGAsICgAAAA=="]]}, 37.9], [{"py/object": "datetime.datetime", "__reduce__": [{"py/type": "datetime.datetime"}, ["B+MFGAsMDQAAAA=="]]}, 37.9], [{"py/object": "datetime.datetime", "__reduce__": [{"py/type": "datetime.datetime"}, ["B+MFGAsTGQAAAA=="]]}, 37.92], [{"py/object": "datetime.datetime", "__reduce__": [{"py/type": "datetime.datetime"}, ["B+MFGAsaGAAAAA=="]]}, 37.92], [{"py/object": "datetime.datetime", "__reduce__": [{"py/type": "datetime.datetime"}, ["B+MFGAsdKQAAAA=="]]}, 38], [{"py/object": "datetime.datetime", "__reduce__": [{"py/type": "datetime.datetime"}, ["B+MFGAsfKAAAAA=="]]}, 37.9], [{"py/object": "datetime.datetime", "__reduce__": [{"py/type": "datetime.datetime"}, ["B+MFGAsqBgAAAA=="]]}, 37.8], [{"py/object": "datetime.datetime", "__reduce__": [{"py/type": "datetime.datetime"}, ["B+MFGAswEAAAAA=="]]}, 37.84], [{"py/object": "datetime.datetime", "__reduce__": [{"py/type": "datetime.datetime"}, ["B+MFGAs6NQAAAA=="]]}, 37.74], [{"py/object": "datetime.datetime", "__reduce__": [{"py/type": "datetime.datetime"}, ["B+MFGAwAKAAAAA=="]]}, 37.7], [{"py/object": "datetime.datetime", "__reduce__": [{"py/type": "datetime.datetime"}, ["B+MFGAwPMwAAAA=="]]}, 37.68], [{"py/object": "datetime.datetime", "__reduce__": [{"py/type": "datetime.datetime"}, ["B+MFGAwSIgAAAA=="]]}, 37.58], [{"py/object": "datetime.datetime", "__reduce__": [{"py/type": "datetime.datetime"}, ["B+MFGAwWMwAAAA=="]]}, 37.6], [{"py/object": "datetime.datetime", "__reduce__": [{"py/type": "datetime.datetime"}, ["B+MFGAwXCgAAAA=="]]}, 37.6], [{"py/object": "datetime.datetime", "__reduce__": [{"py/type": "datetime.datetime"}, ["B+MFGAwaHgAAAA=="]]}, 37.68], [{"py/object": "datetime.datetime", "__reduce__": [{"py/type": "datetime.datetime"}, ["B+MFGAweAwAAAA=="]]}, 37.68], [{"py/object": "datetime.datetime", "__reduce__": [{"py/type": "datetime.datetime"}, ["B+MFGAwjKAAAAA=="]]}, 37.6], [{"py/object": "datetime.datetime", "__reduce__": [{"py/type": "datetime.datetime"}, ["B+MFGAwmFQAAAA=="]]}, 37.7], [{"py/object": "datetime.datetime", "__reduce__": [{"py/type": "datetime.datetime"}, ["B+MFGAwoIgAAAA=="]]}, 37.7], [{"py/object": "datetime.datetime", "__reduce__": [{"py/type": "datetime.datetime"}, ["B+MFGAwuGwAAAA=="]]}, 37.6], [{"py/object": "datetime.datetime", "__reduce__": [{"py/type": "datetime.datetime"}, ["B+MFGAw1AAAAAA=="]]}, 37.7], [{"py/object": "datetime.datetime", "__reduce__": [{"py/type": "datetime.datetime"}, ["B+MFGAw4HQAAAA=="]]}, 37.8], [{"py/object": "datetime.datetime", "__reduce__": [{"py/type": "datetime.datetime"}, ["B+MFGA0BEgAAAA=="]]}, 37.8], [{"py/object": "datetime.datetime", "__reduce__": [{"py/type": "datetime.datetime"}, ["B+MFGA0DMAAAAA=="]]}, 37.76], [{"py/object": "datetime.datetime", "__reduce__": [{"py/type": "datetime.datetime"}, ["B+MFGA0GHQAAAA=="]]}, 38.02], [{"py/object": "datetime.datetime", "__reduce__": [{"py/type": "datetime.datetime"}, ["B+MFGA0LOAAAAA=="]]}, 38.02], [{"py/object": "datetime.datetime", "__reduce__": [{"py/type": "datetime.datetime"}, ["B+MFGA0SLwAAAA=="]]}, 38.2], [{"py/object": "datetime.datetime", "__reduce__": [{"py/type": "datetime.datetime"}, ["B+MFGA0ULgAAAA=="]]}, 38.02], [{"py/object": "datetime.datetime", "__reduce__": [{"py/type": "datetime.datetime"}, ["B+MFGA0oIAAAAA=="]]}, 38.02], [{"py/object": "datetime.datetime", "__reduce__": [{"py/type": "datetime.datetime"}, ["B+MFGA0uIQAAAA=="]]}, 38.1], [{"py/object": "datetime.datetime", "__reduce__": [{"py/type": "datetime.datetime"}, ["B+MFGA0yGgAAAA=="]]}, 38.12], [{"py/object": "datetime.datetime", "__reduce__": [{"py/type": "datetime.datetime"}, ["B+MFGA03DQAAAA=="]]}, 38.24], [{"py/object": "datetime.datetime", "__reduce__": [{"py/type": "datetime.datetime"}, ["B+MFGA4EAQAAAA=="]]}, 38.1], [{"py/object": "datetime.datetime", "__reduce__": [{"py/type": "datetime.datetime"}, ["B+MFGA4HOQAAAA=="]]}, 38.1], [{"py/object": "datetime.datetime", "__reduce__": [{"py/type": "datetime.datetime"}, ["B+MFGA4QHwAAAA=="]]}, 38.34], [{"py/object": "datetime.datetime", "__reduce__": [{"py/type": "datetime.datetime"}, ["B+MFGA4RJwAAAA=="]]}, 38.22], [{"py/object": "datetime.datetime", "__reduce__": [{"py/type": "datetime.datetime"}, ["B+MFGA4TNwAAAA=="]]}, 38.22], [{"py/object": "datetime.datetime", "__reduce__": [{"py/type": "datetime.datetime"}, ["B+MFGA4WLwAAAA=="]]}, 38.22], [{"py/object": "datetime.datetime", "__reduce__": [{"py/type": "datetime.datetime"}, ["B+MFGA4YIQAAAA=="]]}, 38.6], [{"py/object": "datetime.datetime", "__reduce__": [{"py/type": "datetime.datetime"}, ["B+MFGA4bKQAAAA=="]]}, 38.16], [{"py/object": "datetime.datetime", "__reduce__": [{"py/type": "datetime.datetime"}, ["B+MFGA8EFwAAAA=="]]}, 38.3], [{"py/object": "datetime.datetime", "__reduce__": [{"py/type": "datetime.datetime"}, ["B+MFGA8OKQAAAA=="]]}, 38.7], [{"py/object": "datetime.datetime", "__reduce__": [{"py/type": "datetime.datetime"}, ["B+MFGA8QEwAAAA=="]]}, 38.7], [{"py/object": "datetime.datetime", "__reduce__": [{"py/type": "datetime.datetime"}, ["B+MFGA8SKQAAAA=="]]}, 38.76], [{"py/object": "datetime.datetime", "__reduce__": [{"py/type": "datetime.datetime"}, ["B+MFGA8YLwAAAA=="]]}, 38.62], [{"py/object": "datetime.datetime", "__reduce__": [{"py/type": "datetime.datetime"}, ["B+MFGA8bNwAAAA=="]]}, 38.6], [{"py/object": "datetime.datetime", "__reduce__": [{"py/type": "datetime.datetime"}, ["B+MFGA8mGgAAAA=="]]}, 38.52], [{"py/object": "datetime.datetime", "__reduce__": [{"py/type": "datetime.datetime"}, ["B+MFGA8nIAAAAA=="]]}, 38.68], [{"py/object": "datetime.datetime", "__reduce__": [{"py/type": "datetime.datetime"}, ["B+MFGA8xKQAAAA=="]]}, 38.7], [{"py/object": "datetime.datetime", "__reduce__": [{"py/type": "datetime.datetime"}, ["B+MFGA84BAAAAA=="]]}, 38.7], [{"py/object": "datetime.datetime", "__reduce__": [{"py/type": "datetime.datetime"}, ["B+MFGA87OAAAAA=="]]}, 38.5], [{"py/object": "datetime.datetime", "__reduce__": [{"py/type": "datetime.datetime"}, ["B+MFGBADMAAAAA=="]]}, 38.6], [{"py/object": "datetime.datetime", "__reduce__": [{"py/type": "datetime.datetime"}, ["B+MFGBAQGAAAAA=="]]}, 38.6], [{"py/object": "datetime.datetime", "__reduce__": [{"py/type": "datetime.datetime"}, ["B+MFGBAbEgAAAA=="]]}, 38.6], [{"py/object": "datetime.datetime", "__reduce__": [{"py/type": "datetime.datetime"}, ["B+MFGBAeHwAAAA=="]]}, 38.7], [{"py/object": "datetime.datetime", "__reduce__": [{"py/type": "datetime.datetime"}, ["B+MFGBAgLAAAAA=="]]}, 38.66], [{"py/object": "datetime.datetime", "__reduce__": [{"py/type": "datetime.datetime"}, ["B+MFGBAsNQAAAA=="]]}, 38.58], [{"py/object": "datetime.datetime", "__reduce__": [{"py/type": "datetime.datetime"}, ["B+MFGBAtLwAAAA=="]]}, 38.7], [{"py/object": "datetime.datetime", "__reduce__": [{"py/type": "datetime.datetime"}, ["B+MFGBAvMAAAAA=="]]}, 38.5], [{"py/object": "datetime.datetime", "__reduce__": [{"py/type": "datetime.datetime"}, ["B+MFGBA4HgAAAA=="]]}, 38.5], [{"py/object": "datetime.datetime", "__reduce__": [{"py/type": "datetime.datetime"}, ["B+MFGBEBIQAAAA=="]]}, 38.4], [{"py/object": "datetime.datetime", "__reduce__": [{"py/type": "datetime.datetime"}, ["B+MFGBEGNQAAAA=="]]}, 38.3], [{"py/object": "datetime.datetime", "__reduce__": [{"py/type": "datetime.datetime"}, ["B+MFGBEIJwAAAA=="]]}, 38.5], [{"py/object": "datetime.datetime", "__reduce__": [{"py/type": "datetime.datetime"}, ["B+MFGBERNwAAAA=="]]}, 38.5], [{"py/object": "datetime.datetime", "__reduce__": [{"py/type": "datetime.datetime"}, ["B+MFGBEcEwAAAA=="]]}, 38.5], [{"py/object": "datetime.datetime", "__reduce__": [{"py/type": "datetime.datetime"}, ["B+MFGBEeCgAAAA=="]]}, 38.5], [{"py/object": "datetime.datetime", "__reduce__": [{"py/type": "datetime.datetime"}, ["B+MFGBEtGgAAAA=="]]}, 38.5], [{"py/object": "datetime.datetime", "__reduce__": [{"py/type": "datetime.datetime"}, ["B+MFGBEzEgAAAA=="]]}, 38.6], [{"py/object": "datetime.datetime", "__reduce__": [{"py/type": "datetime.datetime"}, ["B+MFGBIFJgAAAA=="]]}, 38.68], [{"py/object": "datetime.datetime", "__reduce__": [{"py/type": "datetime.datetime"}, ["B+MFGBISDwAAAA=="]]}, 38.7], [{"py/object": "datetime.datetime", "__reduce__": [{"py/type": "datetime.datetime"}, ["B+MFGBIaJwAAAA=="]]}, 38.7], [{"py/object": "datetime.datetime", "__reduce__": [{"py/type": "datetime.datetime"}, ["B+MFGBIcFgAAAA=="]]}, 38.54], [{"py/object": "datetime.datetime", "__reduce__": [{"py/type": "datetime.datetime"}, ["B+MFGBIfAAAAAA=="]]}, 38.7], [{"py/object": "datetime.datetime", "__reduce__": [{"py/type": "datetime.datetime"}, ["B+MFGBIjKgAAAA=="]]}, 38.56], [{"py/object": "datetime.datetime", "__reduce__": [{"py/type": "datetime.datetime"}, ["B+MFGBImFwAAAA=="]]}, 38.6], [{"py/object": "datetime.datetime", "__reduce__": [{"py/type": "datetime.datetime"}, ["B+MFGBInJAAAAA=="]]}, 38.7], [{"py/object": "datetime.datetime", "__reduce__": [{"py/type": "datetime.datetime"}, ["B+MFGBIsIgAAAA=="]]}, 38.62], [{"py/object": "datetime.datetime", "__reduce__": [{"py/type": "datetime.datetime"}, ["B+MFGBIuDAAAAA=="]]}, 38.62], [{"py/object": "datetime.datetime", "__reduce__": [{"py/type": "datetime.datetime"}, ["B+MFGBIwJwAAAA=="]]}, 38.6], [{"py/object": "datetime.datetime", "__reduce__": [{"py/type": "datetime.datetime"}, ["B+MFGBIxFgAAAA=="]]}, 38.6], [{"py/object": "datetime.datetime", "__reduce__": [{"py/type": "datetime.datetime"}, ["B+MFGBMABAAAAA=="]]}, 38.6]]