[{"py/object": "twitter.Twitt", "date": {"py/object": "datetime.datetime", "__reduce__": [{"py/type": "datetime.datetime"}, ["B+MFGBApLgAAAA=="]]}, "id": 1131963509934305282, "ignore": false, "lang": null, "power": 807, "sentiment": 0, "sentimentKeys": [], "text": "@gibon102 A pa\u0144stwo co 2 godz w sobot\u0119 mohito\n\ud83d\ude06 \ud83d\ude06 \ud83d\ude06", "twitt_power": 0, "user": "Wojtek", "user_power": 807}, {"py/object": "twitter.Twitt", "date": {"py/object": "datetime.datetime", "__reduce__": [{"py/type": "datetime.datetime"}, ["B+MFFxUwLwAAAA=="]]}, "id": 1131678387506954241, "ignore": false, "lang": null, "power": 3808, "sentiment": 0, "sentimentKeys": [], "text": "@dalianommori pasowalaby mi super do bucikow, ale 32 jest troch\u0119 jednak za lozne, mohito", "twitt_power": 1, "user": "poppyfairy", "user_power": 3807}, {"py/object": "twitter.Twitt", "date": {"py/object": "datetime.datetime", "__reduce__": [{"py/type": "datetime.datetime"}, ["B+MFFxE3KQAAAA=="]]}, "id": 1131619725123964928, "ignore": false, "lang": null, "power": 31825, "sentiment": 0, "sentimentKeys": [], "text": "tak wygl\u0105dam w pi\u0105tki o sz\u00f3stej rano, bez kawy z ekspresu albo blacka mohito https://t.co/ib9XXr2EtS", "twitt_power": 7, "user": "marcia crocs", "user_power": 31818}, {"py/object": "twitter.Twitt", "date": {"py/object": "datetime.datetime", "__reduce__": [{"py/type": "datetime.datetime"}, ["B+MFFwYnNAAAAA=="]]}, "id": 1131449649024372736, "ignore": false, "lang": null, "power": 1167, "sentiment": 0, "sentimentKeys": [], "text": "@bxanexx Team drinki \ud83e\udd37\ud83c\udffc\u200d\u2640\ufe0f mohito, cosmopolitan \ud83d\udc97", "twitt_power": 0, "user": "NIE JESTEM NOWA", "user_power": 1167}, {"py/object": "twitter.Twitt", "date": {"py/object": "datetime.datetime", "__reduce__": [{"py/type": "datetime.datetime"}, ["B+MFFhQoGAAAAA=="]]}, "id": 1131298788906283008, "ignore": false, "lang": null, "power": 33315, "sentiment": 0, "sentimentKeys": [], "text": "@jimiffee wez ja w sinsay mam 42 a w mohito poni\u017cej xxs", "twitt_power": 0, "user": "emis #ThankYouPristin", "user_power": 33315}, {"py/object": "twitter.Twitt", "date": {"py/object": "datetime.datetime", "__reduce__": [{"py/type": "datetime.datetime"}, ["B+MFFhQeLwAAAA=="]]}, "id": 1131296371024244736, "ignore": false, "lang": null, "power": 30673, "sentiment": 0, "sentimentKeys": [], "text": "@bxanexx piwo smakowe, wino truskawkowe, mohito a najlepiej darmowe", "twitt_power": 0, "user": "\ud835\ude91\ud835\ude98\ud835\ude99\ud835\ude8e\ud835\ude95\ud835\ude8e\ud835\ude9c\ud835\ude9c\ud83e\udd40\u25df\u033d\u25de\u033d", "user_power": 30673}, {"py/object": "twitter.Twitt", "date": {"py/object": "datetime.datetime", "__reduce__": [{"py/type": "datetime.datetime"}, ["B+MFFhQFEAAAAA=="]]}, "id": 1131289947447730176, "ignore": false, "lang": null, "power": 21104, "sentiment": 0, "sentimentKeys": [], "text": "@bxanexx Rum/mohito, piwko jakie\u015b smakowe/despy i winko", "twitt_power": 0, "user": "adriana \ud83e\udd8b", "user_power": 21104}, {"py/object": "twitter.Twitt", "date": {"py/object": "datetime.datetime", "__reduce__": [{"py/type": "datetime.datetime"}, ["B+MFFhMJBwAAAA=="]]}, "id": 1131275816032186370, "ignore": false, "lang": null, "power": 6483, "sentiment": 0, "sentimentKeys": [], "text": "@bxanexx Gin bia\u0142y (mohito)", "twitt_power": 0, "user": "topshop princess", "user_power": 6483}, {"py/object": "twitter.Twitt", "date": {"py/object": "datetime.datetime", "__reduce__": [{"py/type": "datetime.datetime"}, ["B+MFFgsEGwAAAA=="]]}, "id": 1131153845009211392, "ignore": false, "lang": null, "power": 31474, "sentiment": 0, "sentimentKeys": [], "text": "by\u0142am w mohito, chcia\u0142am kupi\u0107 ficik ale S by\u0142o na mnie za du\u017ce, a XS wyprzedane \ud83d\ude43", "twitt_power": 0, "user": "\ud835\udd36\ud835\udd22\ud835\udd34\ud835\udd2c\ud835\udd2b", "user_power": 31474}, {"py/object": "twitter.Twitt", "date": {"py/object": "datetime.datetime", "__reduce__": [{"py/type": "datetime.datetime"}, ["B+MFFgQaCwAAAA=="]]}, "id": 1131053621158862848, "ignore": false, "lang": null, "power": 25973, "sentiment": 0, "sentimentKeys": [], "text": "@neonpunch3 Serio? Ejj a to z Mohito jest?", "twitt_power": 1, "user": "w.\u1d05.\u0274.\u1d1c \u2661", "user_power": 25972}, {"py/object": "twitter.Twitt", "date": {"py/object": "datetime.datetime", "__reduce__": [{"py/type": "datetime.datetime"}, ["B+MFFRYoMgAAAA=="]]}, "id": 1130966707298865153, "ignore": false, "lang": null, "power": 19235, "sentiment": 0, "sentimentKeys": [], "text": "Smak Mohito to b\u0119dzie smak wakacji 2019", "twitt_power": 0, "user": "julu lulu", "user_power": 19235}, {"py/object": "twitter.Twitt", "date": {"py/object": "datetime.datetime", "__reduce__": [{"py/type": "datetime.datetime"}, ["B+MFFRQGOAAAAA=="]]}, "id": 1130927978773438465, "ignore": false, "lang": null, "power": 5157, "sentiment": 0, "sentimentKeys": [], "text": "we stan pan w barze ktory jakims cudem daje mi mohito z alkoholem jak zamawiam bez", "twitt_power": 1, "user": "\ud835\udd87", "user_power": 5156}, {"py/object": "twitter.Twitt", "date": {"py/object": "datetime.datetime", "__reduce__": [{"py/type": "datetime.datetime"}, ["B+MFFQ8ACQAAAA=="]]}, "id": 1130850772759982080, "ignore": false, "lang": null, "power": 30145, "sentiment": 0, "sentimentKeys": [], "text": "@s_weetener_ Og\u00f3lnie to zale\u017cy w jakim mie\u015bcie mieszkasz. W niekt\u00f3rych sieci\u00f3wka s\u0105 spoko, pojedyncze rzeczy, ale zale\u017cy od pow. sklepu. W Mohito i Monnari jest zawsze sporo sukienek z tego, co kojarz\u0119. Je\u015bli w twoim mie\u015bcie s\u0105 jakie\u015b butiki, to tam r\u00f3wnie\u017c warto zajrze\u0107 \u2764\ufe0f", "twitt_power": 1, "user": "Juli\u00e9 saw Shawn", "user_power": 30144}, {"py/object": "twitter.Twitt", "date": {"py/object": "datetime.datetime", "__reduce__": [{"py/type": "datetime.datetime"}, ["B+MFFQ0ILgAAAA=="]]}, "id": 1130822745275666432, "ignore": false, "lang": null, "power": 13407, "sentiment": 0, "sentimentKeys": [], "text": "@littlestarlea nwm czy bra\u0107 t\u0105 \u0142adn\u0105 kiecke z mohito ze sob\u0105", "twitt_power": 0, "user": "`", "user_power": 13407}, {"py/object": "twitter.Twitt", "date": {"py/object": "datetime.datetime", "__reduce__": [{"py/type": "datetime.datetime"}, ["B+MFFQwcLAAAAA=="]]}, "id": 1130812667600494592, "ignore": false, "lang": null, "power": 7826, "sentiment": 0, "sentimentKeys": [], "text": "Wiec podsumowuj\u0105c dzisiejszy dzie\u0144:\nBy\u0142am na dniu otwartym w szk\u00f3\u0142ce indywidualnie z 2kole\u017cankami \nZrobi\u0142am bezrumowe mohito z mi\u0142ym i fajnym typiarzem i je wypi\u0142am\nWygra\u0142am quiz o lotnictwie \nP\u0142aka\u0142am bo kazali mi ta\u0144czy\u0107 a ja chcia\u0142am ale nie umia\u0142am si\u0119 ruszy\u0107+atak paniki :)", "twitt_power": 0, "user": "\ud83c\udf19Lad\u017cer\ud83c\udf19", "user_power": 7826}, {"py/object": "twitter.Twitt", "date": {"py/object": "datetime.datetime", "__reduce__": [{"py/type": "datetime.datetime"}, ["B+MFFQsaDgAAAA=="]]}, "id": 1130796941628067840, "ignore": false, "lang": null, "power": 6660, "sentiment": 0, "sentimentKeys": [], "text": "lody mohito to moje nowe ulubione lody", "twitt_power": 1, "user": "M\u1d00\u0280\u1d1b\u1d1c\u0274\u026a\u1d00", "user_power": 6659}, {"py/object": "twitter.Twitt", "date": {"py/object": "datetime.datetime", "__reduce__": [{"py/type": "datetime.datetime"}, ["B+MFFBUnAQAAAA=="]]}, "id": 1130588765737635840, "ignore": false, "lang": null, "power": 12777, "sentiment": 0, "sentimentKeys": [], "text": "@jungwuuwu @yvesllite w mohito albo w zarze widzia\u0142am podobn\u0105", "twitt_power": 1, "user": "\ud835\udc89\ud835\udc90\ud835\udc94\ud835\udc8a\ud835\udc82 \u02e1\u1d52\u1d5b\u1d49\u02e2 \u02e2\u1d4f\u1dbb [hiatus do 30 maja]", "user_power": 12776}, {"py/object": "twitter.Twitt", "date": {"py/object": "datetime.datetime", "__reduce__": [{"py/type": "datetime.datetime"}, ["B+MFFBQtJwAAAA=="]]}, "id": 1130575336217960448, "ignore": false, "lang": null, "power": 58455, "sentiment": 0, "sentimentKeys": [], "text": "@uforenlig Wiem w\u0142a\u015bnie, ze jeszcze Mohito(idk czy dobrze napisa\u0142am). To jest przera\u017caj\u0105ce, co ludzie robi\u0105 dla pieni\u0119dzy...", "twitt_power": 1, "user": "Poduszka O'Briena \u2728", "user_power": 58454}, {"py/object": "twitter.Twitt", "date": {"py/object": "datetime.datetime", "__reduce__": [{"py/type": "datetime.datetime"}, ["B+MFFBMnKgAAAA=="]]}, "id": 1130558738665021441, "ignore": false, "lang": null, "power": 9936, "sentiment": 0, "sentimentKeys": [], "text": "@Iovsletters kiedys wididzialam jak pare lasek z twittera kupowalo w mohito?? moze tsm poszukaj ponoc ladne byly:|", "twitt_power": 2, "user": "\ud835\udc28\ud835\udc25\ud835\udc1e\ud835\udc27\ud835\udc24\ud835\udc1a \u1d54\u1d25\u1d54", "user_power": 9934}, {"py/object": "twitter.Twitt", "date": {"py/object": "datetime.datetime", "__reduce__": [{"py/type": "datetime.datetime"}, ["B+MFFBAmBQAAAA=="]]}, "id": 1130513034059931648, "ignore": false, "lang": null, "power": 1704, "sentiment": 0, "sentimentKeys": [], "text": "@_nasagirl Mohito, ale spr\u00f3buj na ASOS", "twitt_power": 1, "user": ".", "user_power": 1703}, {"py/object": "twitter.Twitt", "date": {"py/object": "datetime.datetime", "__reduce__": [{"py/type": "datetime.datetime"}, ["B+MFFAwpHwAAAA=="]]}, "id": 1130453500226396160, "ignore": false, "lang": null, "power": 6483, "sentiment": 0, "sentimentKeys": [], "text": "@przykran Ja limonki to do Mohito bior\u0119. Xd", "twitt_power": 0, "user": "topshop princess", "user_power": 6483}, {"py/object": "twitter.Twitt", "date": {"py/object": "datetime.datetime", "__reduce__": [{"py/type": "datetime.datetime"}, ["B+MFFAgOGAAAAA=="]]}, "id": 1130386275083722752, "ignore": false, "lang": null, "power": 1462, "sentiment": 0, "sentimentKeys": [], "text": "@wad3ra fair enough ale wzmacniaja mohito wodka i maja kosmiczne ceny, niewarte sa ich te rzeczy", "twitt_power": 0, "user": "talik \u2757BIO\u2757", "user_power": 1462}, {"py/object": "twitter.Twitt", "date": {"py/object": "datetime.datetime", "__reduce__": [{"py/type": "datetime.datetime"}, ["B+MFExYjLQAAAA=="]]}, "id": 1130240653387083777, "ignore": false, "lang": null, "power": 18084, "sentiment": 0, "sentimentKeys": [], "text": "Wgl kupi\u0142am ciuszki z mohito i reserved za po\u0142ow\u0119 ceny. I one s\u0105 takie \u015bliczne", "twitt_power": 0, "user": "\ud835\udc13\ud835\udc1a\ud835\udc23\ud835\udc1a", "user_power": 18084}, {"py/object": "twitter.Twitt", "date": {"py/object": "datetime.datetime", "__reduce__": [{"py/type": "datetime.datetime"}, ["B+MFExQUEQAAAA=="]]}, "id": 1130206564038709253, "ignore": false, "lang": null, "power": 3572, "sentiment": 0, "sentimentKeys": [], "text": "@opsmykarol @lovinguurl patrz mohito, \u017ce tez ju\u017c nie mo\u017cesz dac cytatu do ksi\u0119gi pami\u0105tkowej", "twitt_power": 0, "user": "QUEEN B\ud83d\udc8e\ud83d\udc51", "user_power": 3572}, {"py/object": "twitter.Twitt", "date": {"py/object": "datetime.datetime", "__reduce__": [{"py/type": "datetime.datetime"}, ["B+MFExEXKwAAAA=="]]}, "id": 1130162128499949568, "ignore": false, "lang": null, "power": 14091, "sentiment": 0, "sentimentKeys": [], "text": "@svsanttz popatrz na wassyl, lou albo na Zalando tez s\u0105 ladniutkie, mo\u017ce mohito tez?", "twitt_power": 1, "user": "agacior\ud83c\udf43", "user_power": 14090}, {"py/object": "twitter.Twitt", "date": {"py/object": "datetime.datetime", "__reduce__": [{"py/type": "datetime.datetime"}, ["B+MFEwwnAQAAAA=="]]}, "id": 1130090481185173505, "ignore": false, "lang": null, "power": 24536, "sentiment": 0, "sentimentKeys": [], "text": "@_oxygenation mohito mniam", "twitt_power": 1, "user": "\u03f2\u03b1\u044f\u043c\u0454\u0438\ud83c\udf88", "user_power": 24535}, {"py/object": "twitter.Twitt", "date": {"py/object": "datetime.datetime", "__reduce__": [{"py/type": "datetime.datetime"}, ["B+MFEwwaOAAAAA=="]]}, "id": 1130087439740153856, "ignore": false, "lang": null, "power": 3341, "sentiment": 0, "sentimentKeys": [], "text": "@yunec Polecam mohito z truskawkami i bazyli\u0105. Poezja.", "twitt_power": 1, "user": "Artur Stanicki", "user_power": 3340}, {"py/object": "twitter.Twitt", "date": {"py/object": "datetime.datetime", "__reduce__": [{"py/type": "datetime.datetime"}, ["B+MFEwoxEQAAAA=="]]}, "id": 1130062867976327168, "ignore": false, "lang": null, "power": 8131, "sentiment": 0, "sentimentKeys": [], "text": "ja wczoraj: *wypi\u0142a dwa wina, osiem browar\u00f3w, 10 kieliszk\u00f3w w\u00f3dki popitych blaczkiem mohito a to wszystko w trzecim dniu chlania po dw\u00f3ch godzinach snu*\n\nja dzisiaj: DlAcZeGo JeStEm JeSzCzE nIeTrZe\u0179wa???!!!", "twitt_power": 1, "user": "kajtek.", "user_power": 8130}, {"py/object": "twitter.Twitt", "date": {"py/object": "datetime.datetime", "__reduce__": [{"py/type": "datetime.datetime"}, ["B+MFEwkOHAAAAA=="]]}, "id": 1130039004148174849, "ignore": false, "lang": null, "power": 34038, "sentiment": 0, "sentimentKeys": [], "text": "@WonderW92953815 @SolakKrzysztof Ta do Mohito ju\u017c si\u0119 nadaje \ud83d\udc4c", "twitt_power": 2, "user": "Piotr Paradoks \ud83d\udcaf\ud83c\uddf5\ud83c\uddf1", "user_power": 34036}, {"py/object": "twitter.Twitt", "date": {"py/object": "datetime.datetime", "__reduce__": [{"py/type": "datetime.datetime"}, ["B+MFEhMVMgAAAA=="]]}, "id": 1129829465998204928, "ignore": false, "lang": null, "power": 6484, "sentiment": 0, "sentimentKeys": [], "text": "@dvlfinvk Dobra, ale ja pije tylko smakowe. Xd ewentualnie piwne Mohito", "twitt_power": 1, "user": "topshop princess", "user_power": 6483}, {"py/object": "twitter.Twitt", "date": {"py/object": "datetime.datetime", "__reduce__": [{"py/type": "datetime.datetime"}, ["B+MFEhAwBQAAAA=="]]}, "id": 1129790774734934016, "ignore": false, "lang": null, "power": 2179, "sentiment": 0, "sentimentKeys": [], "text": "Desperados mohito to najlepszy z desperados\u00f3w", "twitt_power": 0, "user": "darling don't", "user_power": 2179}, {"py/object": "twitter.Twitt", "date": {"py/object": "datetime.datetime", "__reduce__": [{"py/type": "datetime.datetime"}, ["B+MFEg8sFAAAAA=="]]}, "id": 1129774728552562690, "ignore": false, "lang": null, "power": 3171, "sentiment": 0, "sentimentKeys": [], "text": "kupi\u0142am sobie desperadosa mohito, przekonam si\u0119 p\u00f3\u017aniej czy jest taki dobry jak wszyscy m\u00f3wi\u0105", "twitt_power": 2, "user": "kamila", "user_power": 3169}, {"py/object": "twitter.Twitt", "date": {"py/object": "datetime.datetime", "__reduce__": [{"py/type": "datetime.datetime"}, ["B+MFEgwgIgAAAA=="]]}, "id": 1129726470665003013, "ignore": false, "lang": null, "power": 8884, "sentiment": 0, "sentimentKeys": [], "text": "A mnie uda\u0142o si\u0119 kupi\u0107 str\u00f3j na bal! Co prawda po d\u0142ugich wojach, ale jako\u015b si\u0119 uda\u0142o i koniec ko\u0144c\u00f3w spodoba\u0142 mi si\u0119 kombinezon i sukienka w Mohito i czu\u0142am si\u0119 w nich tak dobrze, \u017ce kupi\u0142am to i to \ud83e\udd2d nawet uda\u0142o mi si\u0119 kupi\u0107 buty, wi\u0119c teraz zosta\u0142a mi tylko torebka \ud83e\udd70", "twitt_power": 5, "user": "\ud835\udcdb\ud835\udcea\ud835\udcfe\ud835\udcfb\ud835\udcea\ud83c\udf39", "user_power": 8879}, {"py/object": "twitter.Twitt", "date": {"py/object": "datetime.datetime", "__reduce__": [{"py/type": "datetime.datetime"}, ["B+MFEgswKwAAAA=="]]}, "id": 1129715434297712642, "ignore": false, "lang": null, "power": 38040, "sentiment": 0, "sentimentKeys": [], "text": "maj\u0105 w lidlu desperadosa mohito, od teraz moje \u017cycie b\u0119dzie prostsze :')", "twitt_power": 3, "user": "julke", "user_power": 38037}, {"py/object": "twitter.Twitt", "date": {"py/object": "datetime.datetime", "__reduce__": [{"py/type": "datetime.datetime"}, ["B+MFEgENJwAAAA=="]]}, "id": 1129555615993466880, "ignore": false, "lang": null, "power": 157668, "sentiment": 0, "sentimentKeys": [], "text": "Wypilam szampana, \u0142yka mohito z alkoholem i cale bezalkoholowe, pidczas gdy polowa sie upila i martwilam sie o nich...", "twitt_power": 0, "user": "lil teapot \ud83d\udc9c\ud83e\udde1 jeba\u0107 pledis", "user_power": 157668}, {"py/object": "twitter.Twitt", "date": {"py/object": "datetime.datetime", "__reduce__": [{"py/type": "datetime.datetime"}, ["B+MFEgAcGwAAAA=="]]}, "id": 1129544242257375234, "ignore": false, "lang": null, "power": 25622, "sentiment": 0, "sentimentKeys": [], "text": "ok, mohito to jednak zdradziecke g\u00f3wno, nie ufajcie temu", "twitt_power": 0, "user": "\ud835\ude2a \ud835\ude34\ud835\ude22\ud835\ude38 \ud835\ude2f\ud835\ude2a\ud835\ude22\ud835\ude2d\ud835\ude2d", "user_power": 25622}, {"py/object": "twitter.Twitt", "date": {"py/object": "datetime.datetime", "__reduce__": [{"py/type": "datetime.datetime"}, ["B+MFEgAGFQAAAA=="]]}, "id": 1129538680689975296, "ignore": false, "lang": null, "power": 1101, "sentiment": 0, "sentimentKeys": [], "text": "Moja mama si\u0119 zdziwi\u0142a, \u017ce wr\u00f3ci\u0142am tak trze\u017awa do domu. Ale patrz\u0105c ile wypi\u0142am, i to na pusty \u017co\u0142\u0105dek, sama si\u0119 dziwi\u0119. Teraz musz\u0119 co\u015b zje\u015b\u0107, ale cholera, jest za p\u00f3\u017ano xD i cholera, ostatecznie nie wypi\u0142am mojego mohito.... Musz\u0119 to nadrobi\u0107 https://t.co/f61rAUR5EH", "twitt_power": 0, "user": "Red Cobweb \u096a", "user_power": 1101}, {"py/object": "twitter.Twitt", "date": {"py/object": "datetime.datetime", "__reduce__": [{"py/type": "datetime.datetime"}, ["B+MFERYrDwAAAA=="]]}, "id": 1129517767714115584, "ignore": false, "lang": null, "power": 19235, "sentiment": 0, "sentimentKeys": [], "text": "17.05 \n3j \nZwierzenia \nMohito", "twitt_power": 0, "user": "julu lulu", "user_power": 19235}, {"py/object": "twitter.Twitt", "date": {"py/object": "datetime.datetime", "__reduce__": [{"py/type": "datetime.datetime"}, ["B+MFERUaMQAAAA=="]]}, "id": 1129498530446532609, "ignore": false, "lang": null, "power": 25623, "sentiment": 0, "sentimentKeys": [], "text": "mohito chwyta jak chuj", "twitt_power": 1, "user": "\ud835\ude2a \ud835\ude34\ud835\ude22\ud835\ude38 \ud835\ude2f\ud835\ude2a\ud835\ude22\ud835\ude2d\ud835\ude2d", "user_power": 25622}, {"py/object": "twitter.Twitt", "date": {"py/object": "datetime.datetime", "__reduce__": [{"py/type": "datetime.datetime"}, ["B+MFERIzDQAAAA=="]]}, "id": 1129459374974558208, "ignore": false, "lang": null, "power": 2557, "sentiment": 0, "sentimentKeys": [], "text": "vegan guru na ig - smoothie jarmuz 20 razy dziennie 3 litry wody duzo swierzego powietrza:))((((\n\nvegan ja - *wpierdala ramen za 2zl z lidla popija energetykiem o smaku mohito/stopiony plastik i czysci nos z krwi po wciaganiu skruszonych lekow nasennych", "twitt_power": 1, "user": "u     t w a t", "user_power": 2556}, {"py/object": "twitter.Twitt", "date": {"py/object": "datetime.datetime", "__reduce__": [{"py/type": "datetime.datetime"}, ["B+MFEQUjGwAAAA=="]]}, "id": 1129259113299533825, "ignore": false, "lang": null, "power": 19634, "sentiment": 0, "sentimentKeys": [], "text": "@chiisaihaizou Mohito lepszy", "twitt_power": 1, "user": "Kulix\u00b9\u00b2\u2077 will see SUNMI \ud83c\udff3\ufe0f\u200d\ud83c\udf08", "user_power": 19633}, {"py/object": "twitter.Twitt", "date": {"py/object": "datetime.datetime", "__reduce__": [{"py/type": "datetime.datetime"}, ["B+MFEQUQAgAAAA=="]]}, "id": 1129254223315722240, "ignore": false, "lang": null, "power": 43823, "sentiment": 0, "sentimentKeys": [], "text": "mam tak\u0105 ochot\u0119 na mohito \u017ce argh", "twitt_power": 0, "user": "nelly", "user_power": 43823}, {"py/object": "twitter.Twitt", "date": {"py/object": "datetime.datetime", "__reduce__": [{"py/type": "datetime.datetime"}, ["B+MFEQELFgAAAA=="]]}, "id": 1129192652619038720, "ignore": false, "lang": null, "power": 2521, "sentiment": 0, "sentimentKeys": [], "text": "mohito ma ostatnio bardzo dziwna rozmiar\u00f3wk\u0119 \ud83d\ude14 musz\u0119 przej\u015b\u0107 si\u0119 do innego sklepu, przymierzy\u0107 XS mo\u017ce b\u0119d\u0105 lepiej le\u017ce\u0107", "twitt_power": 0, "user": "\ud835\udcc5\ud835\udcb6\ud835\udcca\ud835\udcc1\ud835\udcbe\ud835\udcc3\ud835\udcb6", "user_power": 2521}]